{"20000101":{"date":"20000101","cnDay":"六","term":"元旦","day":"1","month":"1","year":"2000","legalHoliday":"元旦节"},"20000102":{"date":"20000102","cnDay":"日","day":"2","month":"1","year":"2000","legalHoliday":"元旦节"},"20000103":{"date":"20000103","cnDay":"一","day":"3","month":"1","year":"2000"},"20000104":{"date":"20000104","cnDay":"二","day":"4","month":"1","year":"2000"},"20000105":{"date":"20000105","cnDay":"三","day":"5","month":"1","year":"2000"},"20000106":{"date":"20000106","cnDay":"四","term":"小寒","day":"6","month":"1","year":"2000"},"20000107":{"date":"20000107","cnDay":"五","day":"7","month":"1","year":"2000"},"20000108":{"date":"20000108","cnDay":"六","day":"8","month":"1","year":"2000"},"20000109":{"date":"20000109","cnDay":"日","day":"9","month":"1","year":"2000"},"20000110":{"date":"20000110","cnDay":"一","day":"10","month":"1","year":"2000"},"20000111":{"date":"20000111","cnDay":"二","day":"11","month":"1","year":"2000"},"20000112":{"date":"20000112","cnDay":"三","day":"12","month":"1","year":"2000"},"20000113":{"date":"20000113","cnDay":"四","day":"13","month":"1","year":"2000"},"20000114":{"date":"20000114","cnDay":"五","desc":"腊八节","day":"14","month":"1","year":"2000"},"20000115":{"date":"20000115","cnDay":"六","day":"15","month":"1","year":"2000"},"20000116":{"date":"20000116","cnDay":"日","day":"16","month":"1","year":"2000"},"20000117":{"date":"20000117","cnDay":"一","day":"17","month":"1","year":"2000"},"20000118":{"date":"20000118","cnDay":"二","day":"18","month":"1","year":"2000"},"20000119":{"date":"20000119","cnDay":"三","day":"19","month":"1","year":"2000"},"20000120":{"date":"20000120","cnDay":"四","day":"20","month":"1","year":"2000"},"20000121":{"date":"20000121","cnDay":"五","term":"大寒","day":"21","month":"1","year":"2000"},"20000122":{"date":"20000122","cnDay":"六","day":"22","month":"1","year":"2000"},"20000123":{"date":"20000123","cnDay":"日","day":"23","month":"1","year":"2000"},"20000124":{"date":"20000124","cnDay":"一","day":"24","month":"1","year":"2000"},"20000125":{"date":"20000125","cnDay":"二","day":"25","month":"1","year":"2000"},"20000126":{"date":"20000126","cnDay":"三","day":"26","value":"国际海关日","month":"1","year":"2000"},"20000127":{"date":"20000127","cnDay":"四","day":"27","month":"1","year":"2000"},"20000128":{"date":"20000128","cnDay":"五","day":"28","month":"1","year":"2000"},"20000129":{"date":"20000129","cnDay":"六","term":"北小年","day":"29","month":"1","year":"2000"},"20000130":{"date":"20000130","cnDay":"日","term":"南小年","day":"30","month":"1","year":"2000"},"20000131":{"date":"20000131","cnDay":"一","day":"31","month":"1","year":"2000"},"20000201":{"date":"20000201","cnDay":"二","day":"1","month":"2","year":"2000"},"20000202":{"date":"20000202","cnDay":"三","day":"2","value":"湿地日","month":"2","year":"2000"},"20000203":{"date":"20000203","cnDay":"四","day":"3","month":"2","year":"2000"},"20000204":{"date":"20000204","cnDay":"五","term":"除夕 立春","day":"4","month":"2","year":"2000"},"20000205":{"date":"20000205","cnDay":"六","term":"春节","day":"5","month":"2","year":"2000","legalHoliday":"春节"},"20000206":{"date":"20000206","cnDay":"日","day":"6","month":"2","year":"2000","legalHoliday":"春节"},"20000207":{"date":"20000207","cnDay":"一","day":"7","month":"2","year":"2000"},"20000208":{"date":"20000208","cnDay":"二","day":"8","month":"2","year":"2000"},"20000209":{"date":"20000209","cnDay":"三","day":"9","month":"2","year":"2000"},"20000210":{"date":"20000210","cnDay":"四","day":"10","value":"国际气象节","month":"2","year":"2000"},"20000211":{"date":"20000211","cnDay":"五","day":"11","month":"2","year":"2000"},"20000212":{"date":"20000212","cnDay":"六","day":"12","month":"2","year":"2000"},"20000213":{"date":"20000213","cnDay":"日","day":"13","month":"2","year":"2000"},"20000214":{"date":"20000214","cnDay":"一","term":"情人节","day":"14","month":"2","year":"2000"},"20000215":{"date":"20000215","cnDay":"二","day":"15","month":"2","year":"2000"},"20000216":{"date":"20000216","cnDay":"三","day":"16","month":"2","year":"2000"},"20000217":{"date":"20000217","cnDay":"四","day":"17","month":"2","year":"2000"},"20000218":{"date":"20000218","cnDay":"五","day":"18","month":"2","year":"2000"},"20000219":{"date":"20000219","cnDay":"六","term":"元宵节 雨水","day":"19","month":"2","year":"2000"},"20000220":{"date":"20000220","cnDay":"日","day":"20","month":"2","year":"2000"},"20000221":{"date":"20000221","cnDay":"一","day":"21","month":"2","year":"2000"},"20000222":{"date":"20000222","cnDay":"二","day":"22","month":"2","year":"2000"},"20000223":{"date":"20000223","cnDay":"三","day":"23","month":"2","year":"2000"},"20000224":{"date":"20000224","cnDay":"四","day":"24","month":"2","year":"2000"},"20000225":{"date":"20000225","cnDay":"五","day":"25","month":"2","year":"2000"},"20000226":{"date":"20000226","cnDay":"六","day":"26","month":"2","year":"2000"},"20000227":{"date":"20000227","cnDay":"日","day":"27","month":"2","year":"2000"},"20000228":{"date":"20000228","cnDay":"一","day":"28","month":"2","year":"2000"},"20000229":{"date":"20000229","cnDay":"二","day":"29","month":"2","year":"2000"},"20000301":{"date":"20000301","cnDay":"三","day":"1","value":"国际海豹日","month":"3","year":"2000"},"20000302":{"date":"20000302","cnDay":"四","day":"2","month":"3","year":"2000"},"20000303":{"date":"20000303","cnDay":"五","day":"3","value":"全国爱耳日","month":"3","year":"2000"},"20000304":{"date":"20000304","cnDay":"六","day":"4","month":"3","year":"2000"},"20000305":{"date":"20000305","cnDay":"日","term":"惊蛰","day":"5","value":"雷锋纪念日","month":"3","year":"2000"},"20000306":{"date":"20000306","cnDay":"一","day":"6","month":"3","year":"2000"},"20000307":{"date":"20000307","cnDay":"二","day":"7","value":"女生节 龙头节","month":"3","year":"2000"},"20000308":{"date":"20000308","cnDay":"三","term":"妇女节","day":"8","month":"3","year":"2000"},"20000309":{"date":"20000309","cnDay":"四","day":"9","value":"保护母亲河日","month":"3","year":"2000"},"20000310":{"date":"20000310","cnDay":"五","day":"10","month":"3","year":"2000"},"20000311":{"date":"20000311","cnDay":"六","day":"11","month":"3","year":"2000"},"20000312":{"date":"20000312","cnDay":"日","desc":"植树节","day":"12","month":"3","year":"2000"},"20000313":{"date":"20000313","cnDay":"一","day":"13","month":"3","year":"2000"},"20000314":{"date":"20000314","cnDay":"二","day":"14","value":"国际警察日 白色情人节","month":"3","year":"2000"},"20000315":{"date":"20000315","cnDay":"三","day":"15","value":"消费者权益日","month":"3","year":"2000"},"20000316":{"date":"20000316","cnDay":"四","day":"16","month":"3","year":"2000"},"20000317":{"date":"20000317","cnDay":"五","day":"17","value":"国际航海日","month":"3","year":"2000"},"20000318":{"date":"20000318","cnDay":"六","day":"18","month":"3","year":"2000"},"20000319":{"date":"20000319","cnDay":"日","day":"19","month":"3","year":"2000"},"20000320":{"date":"20000320","cnDay":"一","term":"春分","day":"20","month":"3","year":"2000"},"20000321":{"date":"20000321","cnDay":"二","day":"21","value":"世界儿歌日 世界森林日","month":"3","year":"2000"},"20000322":{"date":"20000322","cnDay":"三","day":"22","value":"世界水日","month":"3","year":"2000"},"20000323":{"date":"20000323","cnDay":"四","day":"23","value":"世界气象日","month":"3","year":"2000"},"20000324":{"date":"20000324","cnDay":"五","day":"24","value":"防治结核病日","month":"3","year":"2000"},"20000325":{"date":"20000325","cnDay":"六","day":"25","month":"3","year":"2000"},"20000326":{"date":"20000326","cnDay":"日","day":"26","month":"3","year":"2000"},"20000327":{"date":"20000327","cnDay":"一","day":"27","value":"学生安全教育日","month":"3","year":"2000"},"20000328":{"date":"20000328","cnDay":"二","day":"28","month":"3","year":"2000"},"20000329":{"date":"20000329","cnDay":"三","day":"29","month":"3","year":"2000"},"20000330":{"date":"20000330","cnDay":"四","day":"30","month":"3","year":"2000"},"20000331":{"date":"20000331","cnDay":"五","day":"31","month":"3","year":"2000"},"20000401":{"date":"20000401","cnDay":"六","term":"愚人节","day":"1","month":"4","year":"2000"},"20000402":{"date":"20000402","cnDay":"日","day":"2","month":"4","year":"2000"},"20000403":{"date":"20000403","cnDay":"一","desc":"寒食节","day":"3","month":"4","year":"2000"},"20000404":{"date":"20000404","cnDay":"二","term":"清明","day":"4","month":"4","year":"2000"},"20000405":{"date":"20000405","cnDay":"三","day":"5","month":"4","year":"2000"},"20000406":{"date":"20000406","cnDay":"四","day":"6","month":"4","year":"2000"},"20000407":{"date":"20000407","cnDay":"五","desc":"上巳节","day":"7","month":"4","year":"2000"},"20000408":{"date":"20000408","cnDay":"六","day":"8","month":"4","year":"2000"},"20000409":{"date":"20000409","cnDay":"日","day":"9","month":"4","year":"2000"},"20000410":{"date":"20000410","cnDay":"一","day":"10","month":"4","year":"2000"},"20000411":{"date":"20000411","cnDay":"二","day":"11","month":"4","year":"2000"},"20000412":{"date":"20000412","cnDay":"三","day":"12","month":"4","year":"2000"},"20000413":{"date":"20000413","cnDay":"四","day":"13","month":"4","year":"2000"},"20000414":{"date":"20000414","cnDay":"五","day":"14","value":"黑色情人节","month":"4","year":"2000"},"20000415":{"date":"20000415","cnDay":"六","day":"15","month":"4","year":"2000"},"20000416":{"date":"20000416","cnDay":"日","day":"16","month":"4","year":"2000"},"20000417":{"date":"20000417","cnDay":"一","day":"17","month":"4","year":"2000"},"20000418":{"date":"20000418","cnDay":"二","day":"18","month":"4","year":"2000"},"20000419":{"date":"20000419","cnDay":"三","day":"19","month":"4","year":"2000"},"20000420":{"date":"20000420","cnDay":"四","term":"谷雨","day":"20","month":"4","year":"2000"},"20000421":{"date":"20000421","cnDay":"五","day":"21","month":"4","year":"2000"},"20000422":{"date":"20000422","cnDay":"六","day":"22","value":"地球日","month":"4","year":"2000"},"20000423":{"date":"20000423","cnDay":"日","day":"23","value":"世界读书日","month":"4","year":"2000"},"20000424":{"date":"20000424","cnDay":"一","day":"24","month":"4","year":"2000"},"20000425":{"date":"20000425","cnDay":"二","day":"25","month":"4","year":"2000"},"20000426":{"date":"20000426","cnDay":"三","day":"26","month":"4","year":"2000"},"20000427":{"date":"20000427","cnDay":"四","day":"27","month":"4","year":"2000"},"20000428":{"date":"20000428","cnDay":"五","day":"28","month":"4","year":"2000"},"20000429":{"date":"20000429","cnDay":"六","day":"29","month":"4","year":"2000"},"20000430":{"date":"20000430","cnDay":"日","day":"30","month":"4","year":"2000"},"20000501":{"date":"20000501","cnDay":"一","term":"劳动节","day":"1","month":"5","year":"2000"},"20000502":{"date":"20000502","cnDay":"二","day":"2","value":"世界哮喘日","month":"5","year":"2000"},"20000503":{"date":"20000503","cnDay":"三","day":"3","month":"5","year":"2000"},"20000504":{"date":"20000504","cnDay":"四","term":"青年节","day":"4","value":"青年节","month":"5","year":"2000"},"20000505":{"date":"20000505","cnDay":"五","term":"立夏","day":"5","month":"5","year":"2000"},"20000506":{"date":"20000506","cnDay":"六","day":"6","month":"5","year":"2000"},"20000507":{"date":"20000507","cnDay":"日","day":"7","month":"5","year":"2000"},"20000508":{"date":"20000508","cnDay":"一","day":"8","value":"世界哮喘日 世界微笑日 世界红十字日","month":"5","year":"2000"},"20000509":{"date":"20000509","cnDay":"二","day":"9","month":"5","year":"2000"},"20000510":{"date":"20000510","cnDay":"三","day":"10","month":"5","year":"2000"},"20000511":{"date":"20000511","cnDay":"四","day":"11","month":"5","year":"2000"},"20000512":{"date":"20000512","cnDay":"五","day":"12","value":"护士节","month":"5","year":"2000"},"20000513":{"date":"20000513","cnDay":"六","day":"13","month":"5","year":"2000"},"20000514":{"date":"20000514","cnDay":"日","term":"母亲节","day":"14","month":"5","year":"2000"},"20000515":{"date":"20000515","cnDay":"一","day":"15","value":"国际家庭日","month":"5","year":"2000"},"20000516":{"date":"20000516","cnDay":"二","day":"16","month":"5","year":"2000"},"20000517":{"date":"20000517","cnDay":"三","day":"17","month":"5","year":"2000"},"20000518":{"date":"20000518","cnDay":"四","day":"18","value":"博物馆日","month":"5","year":"2000"},"20000519":{"date":"20000519","cnDay":"五","day":"19","month":"5","year":"2000"},"20000520":{"date":"20000520","cnDay":"六","day":"20","month":"5","year":"2000"},"20000521":{"date":"20000521","cnDay":"日","term":"小满","day":"21","month":"5","year":"2000"},"20000522":{"date":"20000522","cnDay":"一","day":"22","month":"5","year":"2000"},"20000523":{"date":"20000523","cnDay":"二","day":"23","month":"5","year":"2000"},"20000524":{"date":"20000524","cnDay":"三","day":"24","month":"5","year":"2000"},"20000525":{"date":"20000525","cnDay":"四","day":"25","month":"5","year":"2000"},"20000526":{"date":"20000526","cnDay":"五","day":"26","month":"5","year":"2000"},"20000527":{"date":"20000527","cnDay":"六","day":"27","month":"5","year":"2000"},"20000528":{"date":"20000528","cnDay":"日","day":"28","month":"5","year":"2000"},"20000529":{"date":"20000529","cnDay":"一","day":"29","month":"5","year":"2000"},"20000530":{"date":"20000530","cnDay":"二","day":"30","month":"5","year":"2000"},"20000531":{"date":"20000531","cnDay":"三","day":"31","value":"世界无烟日","month":"5","year":"2000"},"20000601":{"date":"20000601","cnDay":"四","term":"儿童节","day":"1","month":"6","year":"2000"},"20000602":{"date":"20000602","cnDay":"五","day":"2","month":"6","year":"2000"},"20000603":{"date":"20000603","cnDay":"六","day":"3","month":"6","year":"2000"},"20000604":{"date":"20000604","cnDay":"日","day":"4","month":"6","year":"2000"},"20000605":{"date":"20000605","cnDay":"一","term":"芒种","day":"5","value":"环境日","month":"6","year":"2000"},"20000606":{"date":"20000606","cnDay":"二","term":"端午节","day":"6","value":"全国爱眼日","month":"6","year":"2000"},"20000607":{"date":"20000607","cnDay":"三","day":"7","month":"6","year":"2000"},"20000608":{"date":"20000608","cnDay":"四","day":"8","month":"6","year":"2000"},"20000609":{"date":"20000609","cnDay":"五","day":"9","month":"6","year":"2000"},"20000610":{"date":"20000610","cnDay":"六","day":"10","month":"6","year":"2000"},"20000611":{"date":"20000611","cnDay":"日","day":"11","value":"中国人口日","month":"6","year":"2000"},"20000612":{"date":"20000612","cnDay":"一","day":"12","month":"6","year":"2000"},"20000613":{"date":"20000613","cnDay":"二","day":"13","month":"6","year":"2000"},"20000614":{"date":"20000614","cnDay":"三","day":"14","month":"6","year":"2000"},"20000615":{"date":"20000615","cnDay":"四","day":"15","month":"6","year":"2000"},"20000616":{"date":"20000616","cnDay":"五","day":"16","month":"6","year":"2000"},"20000617":{"date":"20000617","cnDay":"六","day":"17","month":"6","year":"2000"},"20000618":{"date":"20000618","cnDay":"日","term":"父亲节","day":"18","month":"6","year":"2000"},"20000619":{"date":"20000619","cnDay":"一","day":"19","month":"6","year":"2000"},"20000620":{"date":"20000620","cnDay":"二","day":"20","month":"6","year":"2000"},"20000621":{"date":"20000621","cnDay":"三","term":"夏至","day":"21","month":"6","year":"2000"},"20000622":{"date":"20000622","cnDay":"四","day":"22","month":"6","year":"2000"},"20000623":{"date":"20000623","cnDay":"五","day":"23","month":"6","year":"2000"},"20000624":{"date":"20000624","cnDay":"六","day":"24","month":"6","year":"2000"},"20000625":{"date":"20000625","cnDay":"日","day":"25","value":"全国土地日","month":"6","year":"2000"},"20000626":{"date":"20000626","cnDay":"一","day":"26","value":"国际禁毒日","month":"6","year":"2000"},"20000627":{"date":"20000627","cnDay":"二","day":"27","month":"6","year":"2000"},"20000628":{"date":"20000628","cnDay":"三","day":"28","month":"6","year":"2000"},"20000629":{"date":"20000629","cnDay":"四","day":"29","month":"6","year":"2000"},"20000630":{"date":"20000630","cnDay":"五","day":"30","month":"6","year":"2000"},"20000701":{"date":"20000701","cnDay":"六","term":"建党节","day":"1","value":"香港回归日","month":"7","year":"2000"},"20000702":{"date":"20000702","cnDay":"日","day":"2","value":"体育记者日","month":"7","year":"2000"},"20000703":{"date":"20000703","cnDay":"一","day":"3","month":"7","year":"2000"},"20000704":{"date":"20000704","cnDay":"二","day":"4","value":"美国独立日","month":"7","year":"2000"},"20000705":{"date":"20000705","cnDay":"三","day":"5","month":"7","year":"2000"},"20000706":{"date":"20000706","cnDay":"四","day":"6","month":"7","year":"2000"},"20000707":{"date":"20000707","cnDay":"五","term":"小暑","day":"7","month":"7","year":"2000"},"20000708":{"date":"20000708","cnDay":"六","day":"8","month":"7","year":"2000"},"20000709":{"date":"20000709","cnDay":"日","day":"9","month":"7","year":"2000"},"20000710":{"date":"20000710","cnDay":"一","day":"10","month":"7","year":"2000"},"20000711":{"date":"20000711","cnDay":"二","day":"11","value":"世界人口日","month":"7","year":"2000"},"20000712":{"date":"20000712","cnDay":"三","day":"12","month":"7","year":"2000"},"20000713":{"date":"20000713","cnDay":"四","day":"13","month":"7","year":"2000"},"20000714":{"date":"20000714","cnDay":"五","day":"14","value":"银色情人节","month":"7","year":"2000"},"20000715":{"date":"20000715","cnDay":"六","day":"15","month":"7","year":"2000"},"20000716":{"date":"20000716","cnDay":"日","day":"16","month":"7","year":"2000"},"20000717":{"date":"20000717","cnDay":"一","day":"17","month":"7","year":"2000"},"20000718":{"date":"20000718","cnDay":"二","day":"18","month":"7","year":"2000"},"20000719":{"date":"20000719","cnDay":"三","day":"19","month":"7","year":"2000"},"20000720":{"date":"20000720","cnDay":"四","day":"20","month":"7","year":"2000"},"20000721":{"date":"20000721","cnDay":"五","day":"21","month":"7","year":"2000"},"20000722":{"date":"20000722","cnDay":"六","term":"大暑","day":"22","month":"7","year":"2000"},"20000723":{"date":"20000723","cnDay":"日","day":"23","month":"7","year":"2000"},"20000724":{"date":"20000724","cnDay":"一","day":"24","month":"7","year":"2000"},"20000725":{"date":"20000725","cnDay":"二","day":"25","value":"火把节","month":"7","year":"2000"},"20000726":{"date":"20000726","cnDay":"三","day":"26","month":"7","year":"2000"},"20000727":{"date":"20000727","cnDay":"四","day":"27","month":"7","year":"2000"},"20000728":{"date":"20000728","cnDay":"五","day":"28","month":"7","year":"2000"},"20000729":{"date":"20000729","cnDay":"六","day":"29","month":"7","year":"2000"},"20000730":{"date":"20000730","cnDay":"日","day":"30","month":"7","year":"2000"},"20000731":{"date":"20000731","cnDay":"一","day":"31","value":"非洲妇女日","month":"7","year":"2000"},"20000801":{"date":"20000801","cnDay":"二","term":"建军节","day":"1","month":"8","year":"2000"},"20000802":{"date":"20000802","cnDay":"三","day":"2","month":"8","year":"2000"},"20000803":{"date":"20000803","cnDay":"四","day":"3","month":"8","year":"2000"},"20000804":{"date":"20000804","cnDay":"五","day":"4","month":"8","year":"2000"},"20000805":{"date":"20000805","cnDay":"六","day":"5","month":"8","year":"2000"},"20000806":{"date":"20000806","cnDay":"日","term":"七夕节","day":"6","month":"8","year":"2000"},"20000807":{"date":"20000807","cnDay":"一","term":"立秋","day":"7","month":"8","year":"2000"},"20000808":{"date":"20000808","cnDay":"二","day":"8","month":"8","year":"2000"},"20000809":{"date":"20000809","cnDay":"三","day":"9","month":"8","year":"2000"},"20000810":{"date":"20000810","cnDay":"四","day":"10","month":"8","year":"2000"},"20000811":{"date":"20000811","cnDay":"五","day":"11","month":"8","year":"2000"},"20000812":{"date":"20000812","cnDay":"六","day":"12","value":"国际青年节","month":"8","year":"2000"},"20000813":{"date":"20000813","cnDay":"日","day":"13","month":"8","year":"2000"},"20000814":{"date":"20000814","cnDay":"一","desc":"中元节","day":"14","month":"8","year":"2000"},"20000815":{"date":"20000815","cnDay":"二","day":"15","month":"8","year":"2000"},"20000816":{"date":"20000816","cnDay":"三","day":"16","month":"8","year":"2000"},"20000817":{"date":"20000817","cnDay":"四","day":"17","month":"8","year":"2000"},"20000818":{"date":"20000818","cnDay":"五","day":"18","month":"8","year":"2000"},"20000819":{"date":"20000819","cnDay":"六","day":"19","month":"8","year":"2000"},"20000820":{"date":"20000820","cnDay":"日","day":"20","month":"8","year":"2000"},"20000821":{"date":"20000821","cnDay":"一","day":"21","month":"8","year":"2000"},"20000822":{"date":"20000822","cnDay":"二","day":"22","month":"8","year":"2000"},"20000823":{"date":"20000823","cnDay":"三","term":"处暑","day":"23","month":"8","year":"2000"},"20000824":{"date":"20000824","cnDay":"四","day":"24","month":"8","year":"2000"},"20000825":{"date":"20000825","cnDay":"五","day":"25","month":"8","year":"2000"},"20000826":{"date":"20000826","cnDay":"六","day":"26","value":"律师咨询日","month":"8","year":"2000"},"20000827":{"date":"20000827","cnDay":"日","day":"27","month":"8","year":"2000"},"20000828":{"date":"20000828","cnDay":"一","day":"28","month":"8","year":"2000"},"20000829":{"date":"20000829","cnDay":"二","day":"29","month":"8","year":"2000"},"20000830":{"date":"20000830","cnDay":"三","day":"30","month":"8","year":"2000"},"20000831":{"date":"20000831","cnDay":"四","day":"31","month":"8","year":"2000"},"20000901":{"date":"20000901","cnDay":"五","day":"1","month":"9","year":"2000"},"20000902":{"date":"20000902","cnDay":"六","day":"2","month":"9","year":"2000"},"20000903":{"date":"20000903","cnDay":"日","day":"3","month":"9","year":"2000"},"20000904":{"date":"20000904","cnDay":"一","day":"4","month":"9","year":"2000"},"20000905":{"date":"20000905","cnDay":"二","day":"5","month":"9","year":"2000"},"20000906":{"date":"20000906","cnDay":"三","day":"6","month":"9","year":"2000"},"20000907":{"date":"20000907","cnDay":"四","term":"白露","day":"7","month":"9","year":"2000"},"20000908":{"date":"20000908","cnDay":"五","day":"8","value":"国际扫盲日 新闻工作者日","month":"9","year":"2000"},"20000909":{"date":"20000909","cnDay":"六","day":"9","month":"9","year":"2000"},"20000910":{"date":"20000910","cnDay":"日","term":"教师节","day":"10","month":"9","year":"2000"},"20000911":{"date":"20000911","cnDay":"一","day":"11","month":"9","year":"2000"},"20000912":{"date":"20000912","cnDay":"二","term":"中秋节","day":"12","month":"9","year":"2000"},"20000913":{"date":"20000913","cnDay":"三","day":"13","month":"9","year":"2000"},"20000914":{"date":"20000914","cnDay":"四","day":"14","month":"9","year":"2000"},"20000915":{"date":"20000915","cnDay":"五","day":"15","month":"9","year":"2000"},"20000916":{"date":"20000916","cnDay":"六","day":"16","value":"中国脑健康日 臭氧层保护日","month":"9","year":"2000"},"20000917":{"date":"20000917","cnDay":"日","day":"17","value":"清洁地球日","month":"9","year":"2000"},"20000918":{"date":"20000918","cnDay":"一","day":"18","value":"九一八纪念日","month":"9","year":"2000"},"20000919":{"date":"20000919","cnDay":"二","day":"19","month":"9","year":"2000"},"20000920":{"date":"20000920","cnDay":"三","day":"20","value":"全国爱牙日","month":"9","year":"2000"},"20000921":{"date":"20000921","cnDay":"四","day":"21","month":"9","year":"2000"},"20000922":{"date":"20000922","cnDay":"五","day":"22","month":"9","year":"2000"},"20000923":{"date":"20000923","cnDay":"六","term":"秋分","day":"23","month":"9","year":"2000"},"20000924":{"date":"20000924","cnDay":"日","day":"24","month":"9","year":"2000"},"20000925":{"date":"20000925","cnDay":"一","day":"25","month":"9","year":"2000"},"20000926":{"date":"20000926","cnDay":"二","day":"26","month":"9","year":"2000"},"20000927":{"date":"20000927","cnDay":"三","day":"27","value":"世界旅游日","month":"9","year":"2000"},"20000928":{"date":"20000928","cnDay":"四","day":"28","month":"9","year":"2000"},"20000929":{"date":"20000929","cnDay":"五","day":"29","month":"9","year":"2000"},"20000930":{"date":"20000930","cnDay":"六","day":"30","month":"9","year":"2000","legalHoliday":"国庆节"},"20001001":{"date":"20001001","cnDay":"日","term":"国庆节","day":"1","value":"国际音乐日","month":"10","year":"2000","legalHoliday":"国庆节"},"20001002":{"date":"20001002","cnDay":"一","day":"2","month":"10","year":"2000"},"20001003":{"date":"20001003","cnDay":"二","day":"3","month":"10","year":"2000"},"20001004":{"date":"20001004","cnDay":"三","day":"4","value":"世界动物日","month":"10","year":"2000"},"20001005":{"date":"20001005","cnDay":"四","day":"5","value":"世界教师日","month":"10","year":"2000"},"20001006":{"date":"20001006","cnDay":"五","term":"重阳节","day":"6","month":"10","year":"2000"},"20001007":{"date":"20001007","cnDay":"六","day":"7","month":"10","year":"2000"},"20001008":{"date":"20001008","cnDay":"日","term":"寒露","day":"8","value":"全国高血压日","month":"10","year":"2000"},"20001009":{"date":"20001009","cnDay":"一","day":"9","value":"世界邮政日","month":"10","year":"2000"},"20001010":{"date":"20001010","cnDay":"二","day":"10","month":"10","year":"2000"},"20001011":{"date":"20001011","cnDay":"三","day":"11","month":"10","year":"2000"},"20001012":{"date":"20001012","cnDay":"四","day":"12","month":"10","year":"2000"},"20001013":{"date":"20001013","cnDay":"五","day":"13","month":"10","year":"2000"},"20001014":{"date":"20001014","cnDay":"六","day":"14","month":"10","year":"2000"},"20001015":{"date":"20001015","cnDay":"日","day":"15","value":"国际盲人节","month":"10","year":"2000"},"20001016":{"date":"20001016","cnDay":"一","day":"16","value":"世界粮食日","month":"10","year":"2000"},"20001017":{"date":"20001017","cnDay":"二","day":"17","month":"10","year":"2000"},"20001018":{"date":"20001018","cnDay":"三","day":"18","month":"10","year":"2000"},"20001019":{"date":"20001019","cnDay":"四","day":"19","month":"10","year":"2000"},"20001020":{"date":"20001020","cnDay":"五","day":"20","month":"10","year":"2000"},"20001021":{"date":"20001021","cnDay":"六","day":"21","month":"10","year":"2000"},"20001022":{"date":"20001022","cnDay":"日","day":"22","month":"10","year":"2000"},"20001023":{"date":"20001023","cnDay":"一","term":"霜降","day":"23","month":"10","year":"2000"},"20001024":{"date":"20001024","cnDay":"二","day":"24","value":"联合国日","month":"10","year":"2000"},"20001025":{"date":"20001025","cnDay":"三","day":"25","month":"10","year":"2000"},"20001026":{"date":"20001026","cnDay":"四","day":"26","month":"10","year":"2000"},"20001027":{"date":"20001027","cnDay":"五","day":"27","value":"寒衣节","month":"10","year":"2000"},"20001028":{"date":"20001028","cnDay":"六","day":"28","month":"10","year":"2000"},"20001029":{"date":"20001029","cnDay":"日","day":"29","month":"10","year":"2000"},"20001030":{"date":"20001030","cnDay":"一","day":"30","month":"10","year":"2000"},"20001031":{"date":"20001031","cnDay":"二","term":"万圣夜","day":"31","month":"10","year":"2000"},"20001101":{"date":"20001101","cnDay":"三","term":"万圣节","day":"1","month":"11","year":"2000"},"20001102":{"date":"20001102","cnDay":"四","day":"2","month":"11","year":"2000"},"20001103":{"date":"20001103","cnDay":"五","day":"3","month":"11","year":"2000"},"20001104":{"date":"20001104","cnDay":"六","day":"4","month":"11","year":"2000"},"20001105":{"date":"20001105","cnDay":"日","day":"5","month":"11","year":"2000"},"20001106":{"date":"20001106","cnDay":"一","day":"6","month":"11","year":"2000"},"20001107":{"date":"20001107","cnDay":"二","term":"立冬","day":"7","month":"11","year":"2000"},"20001108":{"date":"20001108","cnDay":"三","day":"8","value":"记者节","month":"11","year":"2000"},"20001109":{"date":"20001109","cnDay":"四","day":"9","value":"消防宣传日","month":"11","year":"2000"},"20001110":{"date":"20001110","cnDay":"五","desc":"下元节","day":"10","month":"11","year":"2000"},"20001111":{"date":"20001111","cnDay":"六","day":"11","month":"11","year":"2000"},"20001112":{"date":"20001112","cnDay":"日","day":"12","month":"11","year":"2000"},"20001113":{"date":"20001113","cnDay":"一","day":"13","month":"11","year":"2000"},"20001114":{"date":"20001114","cnDay":"二","day":"14","value":"世界糖尿病日","month":"11","year":"2000"},"20001115":{"date":"20001115","cnDay":"三","day":"15","month":"11","year":"2000"},"20001116":{"date":"20001116","cnDay":"四","day":"16","month":"11","year":"2000"},"20001117":{"date":"20001117","cnDay":"五","day":"17","value":"学生日","month":"11","year":"2000"},"20001118":{"date":"20001118","cnDay":"六","day":"18","month":"11","year":"2000"},"20001119":{"date":"20001119","cnDay":"日","day":"19","month":"11","year":"2000"},"20001120":{"date":"20001120","cnDay":"一","day":"20","month":"11","year":"2000"},"20001121":{"date":"20001121","cnDay":"二","day":"21","month":"11","year":"2000"},"20001122":{"date":"20001122","cnDay":"三","term":"小雪","day":"22","month":"11","year":"2000"},"20001123":{"date":"20001123","cnDay":"四","term":"感恩节","day":"23","month":"11","year":"2000"},"20001124":{"date":"20001124","cnDay":"五","day":"24","month":"11","year":"2000"},"20001125":{"date":"20001125","cnDay":"六","day":"25","month":"11","year":"2000"},"20001126":{"date":"20001126","cnDay":"日","day":"26","month":"11","year":"2000"},"20001127":{"date":"20001127","cnDay":"一","day":"27","month":"11","year":"2000"},"20001128":{"date":"20001128","cnDay":"二","day":"28","month":"11","year":"2000"},"20001129":{"date":"20001129","cnDay":"三","day":"29","month":"11","year":"2000"},"20001130":{"date":"20001130","cnDay":"四","day":"30","month":"11","year":"2000"},"20001201":{"date":"20001201","cnDay":"五","day":"1","value":"艾滋病日","month":"12","year":"2000"},"20001202":{"date":"20001202","cnDay":"六","day":"2","month":"12","year":"2000"},"20001203":{"date":"20001203","cnDay":"日","day":"3","value":"国际残疾人日","month":"12","year":"2000"},"20001204":{"date":"20001204","cnDay":"一","day":"4","month":"12","year":"2000"},"20001205":{"date":"20001205","cnDay":"二","day":"5","month":"12","year":"2000"},"20001206":{"date":"20001206","cnDay":"三","day":"6","month":"12","year":"2000"},"20001207":{"date":"20001207","cnDay":"四","term":"大雪","day":"7","month":"12","year":"2000"},"20001208":{"date":"20001208","cnDay":"五","day":"8","month":"12","year":"2000"},"20001209":{"date":"20001209","cnDay":"六","day":"9","month":"12","year":"2000"},"20001210":{"date":"20001210","cnDay":"日","day":"10","value":"世界人权日","month":"12","year":"2000"},"20001211":{"date":"20001211","cnDay":"一","day":"11","month":"12","year":"2000"},"20001212":{"date":"20001212","cnDay":"二","day":"12","month":"12","year":"2000"},"20001213":{"date":"20001213","cnDay":"三","day":"13","month":"12","year":"2000"},"20001214":{"date":"20001214","cnDay":"四","day":"14","month":"12","year":"2000"},"20001215":{"date":"20001215","cnDay":"五","day":"15","value":"强化免疫日","month":"12","year":"2000"},"20001216":{"date":"20001216","cnDay":"六","day":"16","month":"12","year":"2000"},"20001217":{"date":"20001217","cnDay":"日","day":"17","month":"12","year":"2000"},"20001218":{"date":"20001218","cnDay":"一","day":"18","month":"12","year":"2000"},"20001219":{"date":"20001219","cnDay":"二","day":"19","month":"12","year":"2000"},"20001220":{"date":"20001220","cnDay":"三","day":"20","month":"12","year":"2000"},"20001221":{"date":"20001221","cnDay":"四","term":"冬至","day":"21","month":"12","year":"2000"},"20001222":{"date":"20001222","cnDay":"五","day":"22","month":"12","year":"2000"},"20001223":{"date":"20001223","cnDay":"六","day":"23","month":"12","year":"2000"},"20001224":{"date":"20001224","cnDay":"日","term":"平安夜","day":"24","month":"12","year":"2000"},"20001225":{"date":"20001225","cnDay":"一","term":"圣诞节","day":"25","month":"12","year":"2000"},"20001226":{"date":"20001226","cnDay":"二","day":"26","value":"毛泽东诞辰","month":"12","year":"2000"},"20001227":{"date":"20001227","cnDay":"三","day":"27","month":"12","year":"2000"},"20001228":{"date":"20001228","cnDay":"四","day":"28","month":"12","year":"2000"},"20001229":{"date":"20001229","cnDay":"五","day":"29","month":"12","year":"2000"},"20001230":{"date":"20001230","cnDay":"六","day":"30","month":"12","year":"2000"},"20001231":{"date":"20001231","cnDay":"日","day":"31","month":"12","year":"2000"},"20010101":{"date":"20010101","cnDay":"一","term":"元旦","day":"1","month":"1","year":"2001"},"20010102":{"date":"20010102","cnDay":"二","desc":"腊八节","day":"2","month":"1","year":"2001"},"20010103":{"date":"20010103","cnDay":"三","day":"3","month":"1","year":"2001"},"20010104":{"date":"20010104","cnDay":"四","day":"4","month":"1","year":"2001"},"20010105":{"date":"20010105","cnDay":"五","term":"小寒","day":"5","month":"1","year":"2001"},"20010106":{"date":"20010106","cnDay":"六","day":"6","month":"1","year":"2001"},"20010107":{"date":"20010107","cnDay":"日","day":"7","month":"1","year":"2001"},"20010108":{"date":"20010108","cnDay":"一","day":"8","month":"1","year":"2001"},"20010109":{"date":"20010109","cnDay":"二","day":"9","month":"1","year":"2001"},"20010110":{"date":"20010110","cnDay":"三","day":"10","month":"1","year":"2001"},"20010111":{"date":"20010111","cnDay":"四","day":"11","month":"1","year":"2001"},"20010112":{"date":"20010112","cnDay":"五","day":"12","month":"1","year":"2001"},"20010113":{"date":"20010113","cnDay":"六","day":"13","month":"1","year":"2001"},"20010114":{"date":"20010114","cnDay":"日","day":"14","month":"1","year":"2001"},"20010115":{"date":"20010115","cnDay":"一","day":"15","month":"1","year":"2001"},"20010116":{"date":"20010116","cnDay":"二","day":"16","month":"1","year":"2001"},"20010117":{"date":"20010117","cnDay":"三","term":"北小年","day":"17","month":"1","year":"2001"},"20010118":{"date":"20010118","cnDay":"四","term":"南小年","day":"18","month":"1","year":"2001"},"20010119":{"date":"20010119","cnDay":"五","day":"19","month":"1","year":"2001"},"20010120":{"date":"20010120","cnDay":"六","term":"大寒","day":"20","month":"1","year":"2001"},"20010121":{"date":"20010121","cnDay":"日","day":"21","month":"1","year":"2001"},"20010122":{"date":"20010122","cnDay":"一","day":"22","month":"1","year":"2001"},"20010123":{"date":"20010123","cnDay":"二","term":"除夕","day":"23","month":"1","year":"2001"},"20010124":{"date":"20010124","cnDay":"三","term":"春节","day":"24","month":"1","year":"2001"},"20010125":{"date":"20010125","cnDay":"四","day":"25","month":"1","year":"2001"},"20010126":{"date":"20010126","cnDay":"五","day":"26","value":"国际海关日","month":"1","year":"2001"},"20010127":{"date":"20010127","cnDay":"六","day":"27","month":"1","year":"2001"},"20010128":{"date":"20010128","cnDay":"日","day":"28","month":"1","year":"2001"},"20010129":{"date":"20010129","cnDay":"一","day":"29","month":"1","year":"2001"},"20010130":{"date":"20010130","cnDay":"二","day":"30","month":"1","year":"2001"},"20010131":{"date":"20010131","cnDay":"三","day":"31","month":"1","year":"2001"},"20010201":{"date":"20010201","cnDay":"四","day":"1","month":"2","year":"2001"},"20010202":{"date":"20010202","cnDay":"五","day":"2","value":"湿地日","month":"2","year":"2001"},"20010203":{"date":"20010203","cnDay":"六","day":"3","month":"2","year":"2001"},"20010204":{"date":"20010204","cnDay":"日","term":"立春","day":"4","month":"2","year":"2001"},"20010205":{"date":"20010205","cnDay":"一","day":"5","month":"2","year":"2001"},"20010206":{"date":"20010206","cnDay":"二","day":"6","month":"2","year":"2001"},"20010207":{"date":"20010207","cnDay":"三","term":"元宵节","day":"7","month":"2","year":"2001"},"20010208":{"date":"20010208","cnDay":"四","day":"8","month":"2","year":"2001"},"20010209":{"date":"20010209","cnDay":"五","day":"9","month":"2","year":"2001"},"20010210":{"date":"20010210","cnDay":"六","day":"10","value":"国际气象节","month":"2","year":"2001"},"20010211":{"date":"20010211","cnDay":"日","day":"11","month":"2","year":"2001"},"20010212":{"date":"20010212","cnDay":"一","day":"12","month":"2","year":"2001"},"20010213":{"date":"20010213","cnDay":"二","day":"13","month":"2","year":"2001"},"20010214":{"date":"20010214","cnDay":"三","term":"情人节","day":"14","month":"2","year":"2001"},"20010215":{"date":"20010215","cnDay":"四","day":"15","month":"2","year":"2001"},"20010216":{"date":"20010216","cnDay":"五","day":"16","month":"2","year":"2001"},"20010217":{"date":"20010217","cnDay":"六","day":"17","month":"2","year":"2001"},"20010218":{"date":"20010218","cnDay":"日","term":"雨水","day":"18","month":"2","year":"2001"},"20010219":{"date":"20010219","cnDay":"一","day":"19","month":"2","year":"2001"},"20010220":{"date":"20010220","cnDay":"二","day":"20","month":"2","year":"2001"},"20010221":{"date":"20010221","cnDay":"三","day":"21","month":"2","year":"2001"},"20010222":{"date":"20010222","cnDay":"四","day":"22","month":"2","year":"2001"},"20010223":{"date":"20010223","cnDay":"五","day":"23","month":"2","year":"2001"},"20010224":{"date":"20010224","cnDay":"六","day":"24","value":"龙头节","month":"2","year":"2001"},"20010225":{"date":"20010225","cnDay":"日","day":"25","month":"2","year":"2001"},"20010226":{"date":"20010226","cnDay":"一","day":"26","month":"2","year":"2001"},"20010227":{"date":"20010227","cnDay":"二","day":"27","month":"2","year":"2001"},"20010228":{"date":"20010228","cnDay":"三","day":"28","month":"2","year":"2001"},"20010301":{"date":"20010301","cnDay":"四","day":"1","value":"国际海豹日","month":"3","year":"2001"},"20010302":{"date":"20010302","cnDay":"五","day":"2","month":"3","year":"2001"},"20010303":{"date":"20010303","cnDay":"六","day":"3","value":"全国爱耳日","month":"3","year":"2001"},"20010304":{"date":"20010304","cnDay":"日","day":"4","month":"3","year":"2001"},"20010305":{"date":"20010305","cnDay":"一","term":"惊蛰","day":"5","value":"雷锋纪念日","month":"3","year":"2001"},"20010306":{"date":"20010306","cnDay":"二","day":"6","month":"3","year":"2001"},"20010307":{"date":"20010307","cnDay":"三","day":"7","value":"女生节","month":"3","year":"2001"},"20010308":{"date":"20010308","cnDay":"四","term":"妇女节","day":"8","month":"3","year":"2001"},"20010309":{"date":"20010309","cnDay":"五","day":"9","value":"保护母亲河日","month":"3","year":"2001"},"20010310":{"date":"20010310","cnDay":"六","day":"10","month":"3","year":"2001"},"20010311":{"date":"20010311","cnDay":"日","day":"11","month":"3","year":"2001"},"20010312":{"date":"20010312","cnDay":"一","desc":"植树节","day":"12","month":"3","year":"2001"},"20010313":{"date":"20010313","cnDay":"二","day":"13","month":"3","year":"2001"},"20010314":{"date":"20010314","cnDay":"三","day":"14","value":"国际警察日 白色情人节","month":"3","year":"2001"},"20010315":{"date":"20010315","cnDay":"四","day":"15","value":"消费者权益日","month":"3","year":"2001"},"20010316":{"date":"20010316","cnDay":"五","day":"16","month":"3","year":"2001"},"20010317":{"date":"20010317","cnDay":"六","day":"17","value":"国际航海日","month":"3","year":"2001"},"20010318":{"date":"20010318","cnDay":"日","day":"18","value":"全国爱肝日","month":"3","year":"2001"},"20010319":{"date":"20010319","cnDay":"一","day":"19","month":"3","year":"2001"},"20010320":{"date":"20010320","cnDay":"二","term":"春分","day":"20","month":"3","year":"2001"},"20010321":{"date":"20010321","cnDay":"三","day":"21","value":"世界睡眠日 世界儿歌日 世界森林日","month":"3","year":"2001"},"20010322":{"date":"20010322","cnDay":"四","day":"22","value":"世界水日","month":"3","year":"2001"},"20010323":{"date":"20010323","cnDay":"五","day":"23","value":"世界气象日","month":"3","year":"2001"},"20010324":{"date":"20010324","cnDay":"六","day":"24","value":"防治结核病日","month":"3","year":"2001"},"20010325":{"date":"20010325","cnDay":"日","day":"25","month":"3","year":"2001"},"20010326":{"date":"20010326","cnDay":"一","day":"26","value":"学生安全教育日","month":"3","year":"2001"},"20010327":{"date":"20010327","cnDay":"二","desc":"上巳节","day":"27","month":"3","year":"2001"},"20010328":{"date":"20010328","cnDay":"三","day":"28","month":"3","year":"2001"},"20010329":{"date":"20010329","cnDay":"四","day":"29","month":"3","year":"2001"},"20010330":{"date":"20010330","cnDay":"五","day":"30","month":"3","year":"2001"},"20010331":{"date":"20010331","cnDay":"六","day":"31","month":"3","year":"2001"},"20010401":{"date":"20010401","cnDay":"日","term":"愚人节","day":"1","month":"4","year":"2001"},"20010402":{"date":"20010402","cnDay":"一","day":"2","month":"4","year":"2001"},"20010403":{"date":"20010403","cnDay":"二","day":"3","month":"4","year":"2001"},"20010404":{"date":"20010404","cnDay":"三","desc":"寒食节","day":"4","month":"4","year":"2001"},"20010405":{"date":"20010405","cnDay":"四","term":"清明","day":"5","month":"4","year":"2001"},"20010406":{"date":"20010406","cnDay":"五","day":"6","month":"4","year":"2001"},"20010407":{"date":"20010407","cnDay":"六","day":"7","value":"世界卫生日","month":"4","year":"2001"},"20010408":{"date":"20010408","cnDay":"日","day":"8","month":"4","year":"2001"},"20010409":{"date":"20010409","cnDay":"一","day":"9","month":"4","year":"2001"},"20010410":{"date":"20010410","cnDay":"二","day":"10","month":"4","year":"2001"},"20010411":{"date":"20010411","cnDay":"三","day":"11","month":"4","year":"2001"},"20010412":{"date":"20010412","cnDay":"四","day":"12","month":"4","year":"2001"},"20010413":{"date":"20010413","cnDay":"五","day":"13","month":"4","year":"2001"},"20010414":{"date":"20010414","cnDay":"六","day":"14","value":"黑色情人节","month":"4","year":"2001"},"20010415":{"date":"20010415","cnDay":"日","day":"15","month":"4","year":"2001"},"20010416":{"date":"20010416","cnDay":"一","day":"16","month":"4","year":"2001"},"20010417":{"date":"20010417","cnDay":"二","day":"17","month":"4","year":"2001"},"20010418":{"date":"20010418","cnDay":"三","day":"18","month":"4","year":"2001"},"20010419":{"date":"20010419","cnDay":"四","day":"19","month":"4","year":"2001"},"20010420":{"date":"20010420","cnDay":"五","term":"谷雨","day":"20","month":"4","year":"2001"},"20010421":{"date":"20010421","cnDay":"六","day":"21","month":"4","year":"2001"},"20010422":{"date":"20010422","cnDay":"日","day":"22","value":"地球日","month":"4","year":"2001"},"20010423":{"date":"20010423","cnDay":"一","day":"23","value":"世界读书日","month":"4","year":"2001"},"20010424":{"date":"20010424","cnDay":"二","day":"24","month":"4","year":"2001"},"20010425":{"date":"20010425","cnDay":"三","day":"25","month":"4","year":"2001"},"20010426":{"date":"20010426","cnDay":"四","day":"26","value":"知识产权日","month":"4","year":"2001"},"20010427":{"date":"20010427","cnDay":"五","day":"27","month":"4","year":"2001"},"20010428":{"date":"20010428","cnDay":"六","day":"28","month":"4","year":"2001"},"20010429":{"date":"20010429","cnDay":"日","day":"29","month":"4","year":"2001"},"20010430":{"date":"20010430","cnDay":"一","day":"30","month":"4","year":"2001"},"20010501":{"date":"20010501","cnDay":"二","term":"劳动节","day":"1","value":"世界哮喘日","month":"5","year":"2001"},"20010502":{"date":"20010502","cnDay":"三","day":"2","month":"5","year":"2001"},"20010503":{"date":"20010503","cnDay":"四","day":"3","value":"世界哮喘日","month":"5","year":"2001"},"20010504":{"date":"20010504","cnDay":"五","term":"青年节","day":"4","value":"青年节","month":"5","year":"2001"},"20010505":{"date":"20010505","cnDay":"六","term":"立夏","day":"5","month":"5","year":"2001"},"20010506":{"date":"20010506","cnDay":"日","day":"6","month":"5","year":"2001"},"20010507":{"date":"20010507","cnDay":"一","day":"7","month":"5","year":"2001"},"20010508":{"date":"20010508","cnDay":"二","day":"8","value":"世界微笑日 世界红十字日","month":"5","year":"2001"},"20010509":{"date":"20010509","cnDay":"三","day":"9","month":"5","year":"2001"},"20010510":{"date":"20010510","cnDay":"四","day":"10","month":"5","year":"2001"},"20010511":{"date":"20010511","cnDay":"五","day":"11","month":"5","year":"2001"},"20010512":{"date":"20010512","cnDay":"六","day":"12","value":"护士节","month":"5","year":"2001"},"20010513":{"date":"20010513","cnDay":"日","term":"母亲节","day":"13","month":"5","year":"2001"},"20010514":{"date":"20010514","cnDay":"一","day":"14","month":"5","year":"2001"},"20010515":{"date":"20010515","cnDay":"二","day":"15","value":"国际家庭日","month":"5","year":"2001"},"20010516":{"date":"20010516","cnDay":"三","day":"16","month":"5","year":"2001"},"20010517":{"date":"20010517","cnDay":"四","day":"17","month":"5","year":"2001"},"20010518":{"date":"20010518","cnDay":"五","day":"18","value":"博物馆日","month":"5","year":"2001"},"20010519":{"date":"20010519","cnDay":"六","day":"19","month":"5","year":"2001"},"20010520":{"date":"20010520","cnDay":"日","day":"20","value":"学生营养日","month":"5","year":"2001"},"20010521":{"date":"20010521","cnDay":"一","term":"小满","day":"21","month":"5","year":"2001"},"20010522":{"date":"20010522","cnDay":"二","day":"22","value":"生物多样性日","month":"5","year":"2001"},"20010523":{"date":"20010523","cnDay":"三","day":"23","month":"5","year":"2001"},"20010524":{"date":"20010524","cnDay":"四","day":"24","month":"5","year":"2001"},"20010525":{"date":"20010525","cnDay":"五","day":"25","month":"5","year":"2001"},"20010526":{"date":"20010526","cnDay":"六","day":"26","month":"5","year":"2001"},"20010527":{"date":"20010527","cnDay":"日","day":"27","month":"5","year":"2001"},"20010528":{"date":"20010528","cnDay":"一","day":"28","month":"5","year":"2001"},"20010529":{"date":"20010529","cnDay":"二","day":"29","month":"5","year":"2001"},"20010530":{"date":"20010530","cnDay":"三","day":"30","month":"5","year":"2001"},"20010531":{"date":"20010531","cnDay":"四","day":"31","value":"世界无烟日","month":"5","year":"2001"},"20010601":{"date":"20010601","cnDay":"五","term":"儿童节","day":"1","month":"6","year":"2001"},"20010602":{"date":"20010602","cnDay":"六","day":"2","month":"6","year":"2001"},"20010603":{"date":"20010603","cnDay":"日","day":"3","month":"6","year":"2001"},"20010604":{"date":"20010604","cnDay":"一","day":"4","month":"6","year":"2001"},"20010605":{"date":"20010605","cnDay":"二","term":"芒种","day":"5","value":"环境日","month":"6","year":"2001"},"20010606":{"date":"20010606","cnDay":"三","day":"6","value":"全国爱眼日","month":"6","year":"2001"},"20010607":{"date":"20010607","cnDay":"四","day":"7","month":"6","year":"2001"},"20010608":{"date":"20010608","cnDay":"五","day":"8","month":"6","year":"2001"},"20010609":{"date":"20010609","cnDay":"六","day":"9","month":"6","year":"2001"},"20010610":{"date":"20010610","cnDay":"日","day":"10","month":"6","year":"2001"},"20010611":{"date":"20010611","cnDay":"一","day":"11","value":"中国人口日","month":"6","year":"2001"},"20010612":{"date":"20010612","cnDay":"二","day":"12","month":"6","year":"2001"},"20010613":{"date":"20010613","cnDay":"三","day":"13","month":"6","year":"2001"},"20010614":{"date":"20010614","cnDay":"四","day":"14","month":"6","year":"2001"},"20010615":{"date":"20010615","cnDay":"五","day":"15","month":"6","year":"2001"},"20010616":{"date":"20010616","cnDay":"六","day":"16","month":"6","year":"2001"},"20010617":{"date":"20010617","cnDay":"日","term":"父亲节","day":"17","month":"6","year":"2001"},"20010618":{"date":"20010618","cnDay":"一","day":"18","month":"6","year":"2001"},"20010619":{"date":"20010619","cnDay":"二","day":"19","month":"6","year":"2001"},"20010620":{"date":"20010620","cnDay":"三","day":"20","month":"6","year":"2001"},"20010621":{"date":"20010621","cnDay":"四","term":"夏至","day":"21","month":"6","year":"2001"},"20010622":{"date":"20010622","cnDay":"五","day":"22","month":"6","year":"2001"},"20010623":{"date":"20010623","cnDay":"六","day":"23","month":"6","year":"2001"},"20010624":{"date":"20010624","cnDay":"日","day":"24","month":"6","year":"2001"},"20010625":{"date":"20010625","cnDay":"一","term":"端午节","day":"25","value":"全国土地日","month":"6","year":"2001"},"20010626":{"date":"20010626","cnDay":"二","day":"26","value":"国际禁毒日","month":"6","year":"2001"},"20010627":{"date":"20010627","cnDay":"三","day":"27","month":"6","year":"2001"},"20010628":{"date":"20010628","cnDay":"四","day":"28","month":"6","year":"2001"},"20010629":{"date":"20010629","cnDay":"五","day":"29","month":"6","year":"2001"},"20010630":{"date":"20010630","cnDay":"六","day":"30","month":"6","year":"2001"},"20010701":{"date":"20010701","cnDay":"日","term":"建党节","day":"1","value":"香港回归日","month":"7","year":"2001"},"20010702":{"date":"20010702","cnDay":"一","day":"2","value":"体育记者日","month":"7","year":"2001"},"20010703":{"date":"20010703","cnDay":"二","day":"3","month":"7","year":"2001"},"20010704":{"date":"20010704","cnDay":"三","day":"4","value":"美国独立日","month":"7","year":"2001"},"20010705":{"date":"20010705","cnDay":"四","day":"5","month":"7","year":"2001"},"20010706":{"date":"20010706","cnDay":"五","day":"6","month":"7","year":"2001"},"20010707":{"date":"20010707","cnDay":"六","term":"小暑","day":"7","month":"7","year":"2001"},"20010708":{"date":"20010708","cnDay":"日","day":"8","month":"7","year":"2001"},"20010709":{"date":"20010709","cnDay":"一","day":"9","month":"7","year":"2001"},"20010710":{"date":"20010710","cnDay":"二","day":"10","month":"7","year":"2001"},"20010711":{"date":"20010711","cnDay":"三","day":"11","value":"世界人口日","month":"7","year":"2001"},"20010712":{"date":"20010712","cnDay":"四","day":"12","month":"7","year":"2001"},"20010713":{"date":"20010713","cnDay":"五","day":"13","month":"7","year":"2001"},"20010714":{"date":"20010714","cnDay":"六","day":"14","value":"银色情人节","month":"7","year":"2001"},"20010715":{"date":"20010715","cnDay":"日","day":"15","month":"7","year":"2001"},"20010716":{"date":"20010716","cnDay":"一","day":"16","month":"7","year":"2001"},"20010717":{"date":"20010717","cnDay":"二","day":"17","month":"7","year":"2001"},"20010718":{"date":"20010718","cnDay":"三","day":"18","month":"7","year":"2001"},"20010719":{"date":"20010719","cnDay":"四","day":"19","month":"7","year":"2001"},"20010720":{"date":"20010720","cnDay":"五","day":"20","month":"7","year":"2001"},"20010721":{"date":"20010721","cnDay":"六","day":"21","month":"7","year":"2001"},"20010722":{"date":"20010722","cnDay":"日","day":"22","month":"7","year":"2001"},"20010723":{"date":"20010723","cnDay":"一","term":"大暑","day":"23","month":"7","year":"2001"},"20010724":{"date":"20010724","cnDay":"二","day":"24","month":"7","year":"2001"},"20010725":{"date":"20010725","cnDay":"三","day":"25","month":"7","year":"2001"},"20010726":{"date":"20010726","cnDay":"四","day":"26","month":"7","year":"2001"},"20010727":{"date":"20010727","cnDay":"五","day":"27","month":"7","year":"2001"},"20010728":{"date":"20010728","cnDay":"六","day":"28","month":"7","year":"2001"},"20010729":{"date":"20010729","cnDay":"日","day":"29","month":"7","year":"2001"},"20010730":{"date":"20010730","cnDay":"一","day":"30","month":"7","year":"2001"},"20010731":{"date":"20010731","cnDay":"二","day":"31","value":"非洲妇女日","month":"7","year":"2001"},"20010801":{"date":"20010801","cnDay":"三","term":"建军节","day":"1","month":"8","year":"2001"},"20010802":{"date":"20010802","cnDay":"四","day":"2","month":"8","year":"2001"},"20010803":{"date":"20010803","cnDay":"五","day":"3","month":"8","year":"2001"},"20010804":{"date":"20010804","cnDay":"六","day":"4","month":"8","year":"2001"},"20010805":{"date":"20010805","cnDay":"日","day":"5","month":"8","year":"2001"},"20010806":{"date":"20010806","cnDay":"一","day":"6","month":"8","year":"2001"},"20010807":{"date":"20010807","cnDay":"二","term":"立秋","day":"7","month":"8","year":"2001"},"20010808":{"date":"20010808","cnDay":"三","day":"8","month":"8","year":"2001"},"20010809":{"date":"20010809","cnDay":"四","day":"9","month":"8","year":"2001"},"20010810":{"date":"20010810","cnDay":"五","day":"10","month":"8","year":"2001"},"20010811":{"date":"20010811","cnDay":"六","day":"11","month":"8","year":"2001"},"20010812":{"date":"20010812","cnDay":"日","day":"12","value":"国际青年节","month":"8","year":"2001"},"20010813":{"date":"20010813","cnDay":"一","day":"13","value":"火把节","month":"8","year":"2001"},"20010814":{"date":"20010814","cnDay":"二","day":"14","month":"8","year":"2001"},"20010815":{"date":"20010815","cnDay":"三","day":"15","month":"8","year":"2001"},"20010816":{"date":"20010816","cnDay":"四","day":"16","month":"8","year":"2001"},"20010817":{"date":"20010817","cnDay":"五","day":"17","month":"8","year":"2001"},"20010818":{"date":"20010818","cnDay":"六","day":"18","month":"8","year":"2001"},"20010819":{"date":"20010819","cnDay":"日","day":"19","month":"8","year":"2001"},"20010820":{"date":"20010820","cnDay":"一","day":"20","month":"8","year":"2001"},"20010821":{"date":"20010821","cnDay":"二","day":"21","month":"8","year":"2001"},"20010822":{"date":"20010822","cnDay":"三","day":"22","month":"8","year":"2001"},"20010823":{"date":"20010823","cnDay":"四","term":"处暑","day":"23","month":"8","year":"2001"},"20010824":{"date":"20010824","cnDay":"五","day":"24","month":"8","year":"2001"},"20010825":{"date":"20010825","cnDay":"六","term":"七夕节","day":"25","month":"8","year":"2001"},"20010826":{"date":"20010826","cnDay":"日","day":"26","value":"律师咨询日","month":"8","year":"2001"},"20010827":{"date":"20010827","cnDay":"一","day":"27","month":"8","year":"2001"},"20010828":{"date":"20010828","cnDay":"二","day":"28","month":"8","year":"2001"},"20010829":{"date":"20010829","cnDay":"三","day":"29","month":"8","year":"2001"},"20010830":{"date":"20010830","cnDay":"四","day":"30","month":"8","year":"2001"},"20010831":{"date":"20010831","cnDay":"五","day":"31","month":"8","year":"2001"},"20010901":{"date":"20010901","cnDay":"六","day":"1","month":"9","year":"2001"},"20010902":{"date":"20010902","cnDay":"日","desc":"中元节","day":"2","month":"9","year":"2001"},"20010903":{"date":"20010903","cnDay":"一","day":"3","month":"9","year":"2001"},"20010904":{"date":"20010904","cnDay":"二","day":"4","month":"9","year":"2001"},"20010905":{"date":"20010905","cnDay":"三","day":"5","month":"9","year":"2001"},"20010906":{"date":"20010906","cnDay":"四","day":"6","month":"9","year":"2001"},"20010907":{"date":"20010907","cnDay":"五","term":"白露","day":"7","month":"9","year":"2001"},"20010908":{"date":"20010908","cnDay":"六","day":"8","value":"国际扫盲日 新闻工作者日","month":"9","year":"2001"},"20010909":{"date":"20010909","cnDay":"日","day":"9","month":"9","year":"2001"},"20010910":{"date":"20010910","cnDay":"一","term":"教师节","day":"10","month":"9","year":"2001"},"20010911":{"date":"20010911","cnDay":"二","day":"11","month":"9","year":"2001"},"20010912":{"date":"20010912","cnDay":"三","day":"12","month":"9","year":"2001"},"20010913":{"date":"20010913","cnDay":"四","day":"13","month":"9","year":"2001"},"20010914":{"date":"20010914","cnDay":"五","day":"14","month":"9","year":"2001"},"20010915":{"date":"20010915","cnDay":"六","day":"15","month":"9","year":"2001"},"20010916":{"date":"20010916","cnDay":"日","day":"16","value":"清洁地球日 中国脑健康日 臭氧层保护日","month":"9","year":"2001"},"20010917":{"date":"20010917","cnDay":"一","day":"17","month":"9","year":"2001"},"20010918":{"date":"20010918","cnDay":"二","day":"18","value":"九一八纪念日","month":"9","year":"2001"},"20010919":{"date":"20010919","cnDay":"三","day":"19","month":"9","year":"2001"},"20010920":{"date":"20010920","cnDay":"四","day":"20","value":"全国爱牙日","month":"9","year":"2001"},"20010921":{"date":"20010921","cnDay":"五","day":"21","month":"9","year":"2001"},"20010922":{"date":"20010922","cnDay":"六","day":"22","month":"9","year":"2001"},"20010923":{"date":"20010923","cnDay":"日","term":"秋分","day":"23","month":"9","year":"2001"},"20010924":{"date":"20010924","cnDay":"一","day":"24","month":"9","year":"2001"},"20010925":{"date":"20010925","cnDay":"二","day":"25","month":"9","year":"2001"},"20010926":{"date":"20010926","cnDay":"三","day":"26","month":"9","year":"2001"},"20010927":{"date":"20010927","cnDay":"四","day":"27","value":"世界旅游日","month":"9","year":"2001"},"20010928":{"date":"20010928","cnDay":"五","day":"28","month":"9","year":"2001"},"20010929":{"date":"20010929","cnDay":"六","day":"29","month":"9","year":"2001"},"20010930":{"date":"20010930","cnDay":"日","day":"30","month":"9","year":"2001"},"20011001":{"date":"20011001","cnDay":"一","term":"中秋节","day":"1","value":"国际音乐日","month":"10","year":"2001"},"20011002":{"date":"20011002","cnDay":"二","day":"2","month":"10","year":"2001"},"20011003":{"date":"20011003","cnDay":"三","day":"3","month":"10","year":"2001"},"20011004":{"date":"20011004","cnDay":"四","day":"4","value":"世界动物日","month":"10","year":"2001"},"20011005":{"date":"20011005","cnDay":"五","day":"5","value":"世界教师日","month":"10","year":"2001"},"20011006":{"date":"20011006","cnDay":"六","day":"6","month":"10","year":"2001"},"20011007":{"date":"20011007","cnDay":"日","day":"7","month":"10","year":"2001"},"20011008":{"date":"20011008","cnDay":"一","term":"寒露","day":"8","value":"全国高血压日","month":"10","year":"2001"},"20011009":{"date":"20011009","cnDay":"二","day":"9","value":"世界邮政日","month":"10","year":"2001"},"20011010":{"date":"20011010","cnDay":"三","day":"10","month":"10","year":"2001"},"20011011":{"date":"20011011","cnDay":"四","day":"11","month":"10","year":"2001"},"20011012":{"date":"20011012","cnDay":"五","day":"12","month":"10","year":"2001"},"20011013":{"date":"20011013","cnDay":"六","day":"13","month":"10","year":"2001"},"20011014":{"date":"20011014","cnDay":"日","day":"14","month":"10","year":"2001"},"20011015":{"date":"20011015","cnDay":"一","day":"15","value":"国际盲人节","month":"10","year":"2001"},"20011016":{"date":"20011016","cnDay":"二","day":"16","value":"世界粮食日","month":"10","year":"2001"},"20011017":{"date":"20011017","cnDay":"三","day":"17","month":"10","year":"2001"},"20011018":{"date":"20011018","cnDay":"四","day":"18","month":"10","year":"2001"},"20011019":{"date":"20011019","cnDay":"五","day":"19","month":"10","year":"2001"},"20011020":{"date":"20011020","cnDay":"六","day":"20","month":"10","year":"2001"},"20011021":{"date":"20011021","cnDay":"日","day":"21","month":"10","year":"2001"},"20011022":{"date":"20011022","cnDay":"一","day":"22","month":"10","year":"2001"},"20011023":{"date":"20011023","cnDay":"二","term":"霜降","day":"23","month":"10","year":"2001"},"20011024":{"date":"20011024","cnDay":"三","day":"24","value":"联合国日","month":"10","year":"2001"},"20011025":{"date":"20011025","cnDay":"四","term":"重阳节","day":"25","month":"10","year":"2001"},"20011026":{"date":"20011026","cnDay":"五","day":"26","month":"10","year":"2001"},"20011027":{"date":"20011027","cnDay":"六","day":"27","month":"10","year":"2001"},"20011028":{"date":"20011028","cnDay":"日","day":"28","month":"10","year":"2001"},"20011029":{"date":"20011029","cnDay":"一","day":"29","month":"10","year":"2001"},"20011030":{"date":"20011030","cnDay":"二","day":"30","month":"10","year":"2001"},"20011031":{"date":"20011031","cnDay":"三","term":"万圣夜","day":"31","month":"10","year":"2001"},"20011101":{"date":"20011101","cnDay":"四","term":"万圣节","day":"1","month":"11","year":"2001"},"20011102":{"date":"20011102","cnDay":"五","day":"2","month":"11","year":"2001"},"20011103":{"date":"20011103","cnDay":"六","day":"3","month":"11","year":"2001"},"20011104":{"date":"20011104","cnDay":"日","day":"4","month":"11","year":"2001"},"20011105":{"date":"20011105","cnDay":"一","day":"5","month":"11","year":"2001"},"20011106":{"date":"20011106","cnDay":"二","day":"6","month":"11","year":"2001"},"20011107":{"date":"20011107","cnDay":"三","term":"立冬","day":"7","month":"11","year":"2001"},"20011108":{"date":"20011108","cnDay":"四","day":"8","value":"记者节","month":"11","year":"2001"},"20011109":{"date":"20011109","cnDay":"五","day":"9","value":"消防宣传日","month":"11","year":"2001"},"20011110":{"date":"20011110","cnDay":"六","day":"10","month":"11","year":"2001"},"20011111":{"date":"20011111","cnDay":"日","day":"11","month":"11","year":"2001"},"20011112":{"date":"20011112","cnDay":"一","day":"12","month":"11","year":"2001"},"20011113":{"date":"20011113","cnDay":"二","day":"13","month":"11","year":"2001"},"20011114":{"date":"20011114","cnDay":"三","day":"14","value":"世界糖尿病日","month":"11","year":"2001"},"20011115":{"date":"20011115","cnDay":"四","day":"15","value":"寒衣节","month":"11","year":"2001"},"20011116":{"date":"20011116","cnDay":"五","day":"16","month":"11","year":"2001"},"20011117":{"date":"20011117","cnDay":"六","day":"17","value":"学生日","month":"11","year":"2001"},"20011118":{"date":"20011118","cnDay":"日","day":"18","month":"11","year":"2001"},"20011119":{"date":"20011119","cnDay":"一","day":"19","month":"11","year":"2001"},"20011120":{"date":"20011120","cnDay":"二","day":"20","month":"11","year":"2001"},"20011121":{"date":"20011121","cnDay":"三","day":"21","month":"11","year":"2001"},"20011122":{"date":"20011122","cnDay":"四","term":"感恩节 小雪","day":"22","month":"11","year":"2001"},"20011123":{"date":"20011123","cnDay":"五","day":"23","month":"11","year":"2001"},"20011124":{"date":"20011124","cnDay":"六","day":"24","month":"11","year":"2001"},"20011125":{"date":"20011125","cnDay":"日","day":"25","month":"11","year":"2001"},"20011126":{"date":"20011126","cnDay":"一","day":"26","month":"11","year":"2001"},"20011127":{"date":"20011127","cnDay":"二","day":"27","month":"11","year":"2001"},"20011128":{"date":"20011128","cnDay":"三","day":"28","month":"11","year":"2001"},"20011129":{"date":"20011129","cnDay":"四","desc":"下元节","day":"29","month":"11","year":"2001"},"20011130":{"date":"20011130","cnDay":"五","day":"30","month":"11","year":"2001"},"20011201":{"date":"20011201","cnDay":"六","day":"1","value":"艾滋病日","month":"12","year":"2001"},"20011202":{"date":"20011202","cnDay":"日","day":"2","month":"12","year":"2001"},"20011203":{"date":"20011203","cnDay":"一","day":"3","value":"国际残疾人日","month":"12","year":"2001"},"20011204":{"date":"20011204","cnDay":"二","day":"4","month":"12","year":"2001"},"20011205":{"date":"20011205","cnDay":"三","day":"5","month":"12","year":"2001"},"20011206":{"date":"20011206","cnDay":"四","day":"6","month":"12","year":"2001"},"20011207":{"date":"20011207","cnDay":"五","term":"大雪","day":"7","month":"12","year":"2001"},"20011208":{"date":"20011208","cnDay":"六","day":"8","month":"12","year":"2001"},"20011209":{"date":"20011209","cnDay":"日","day":"9","month":"12","year":"2001"},"20011210":{"date":"20011210","cnDay":"一","day":"10","value":"世界人权日","month":"12","year":"2001"},"20011211":{"date":"20011211","cnDay":"二","day":"11","month":"12","year":"2001"},"20011212":{"date":"20011212","cnDay":"三","day":"12","month":"12","year":"2001"},"20011213":{"date":"20011213","cnDay":"四","day":"13","month":"12","year":"2001"},"20011214":{"date":"20011214","cnDay":"五","day":"14","month":"12","year":"2001"},"20011215":{"date":"20011215","cnDay":"六","day":"15","value":"强化免疫日","month":"12","year":"2001"},"20011216":{"date":"20011216","cnDay":"日","day":"16","month":"12","year":"2001"},"20011217":{"date":"20011217","cnDay":"一","day":"17","month":"12","year":"2001"},"20011218":{"date":"20011218","cnDay":"二","day":"18","month":"12","year":"2001"},"20011219":{"date":"20011219","cnDay":"三","day":"19","month":"12","year":"2001"},"20011220":{"date":"20011220","cnDay":"四","day":"20","month":"12","year":"2001"},"20011221":{"date":"20011221","cnDay":"五","day":"21","month":"12","year":"2001"},"20011222":{"date":"20011222","cnDay":"六","term":"冬至","day":"22","month":"12","year":"2001"},"20011223":{"date":"20011223","cnDay":"日","day":"23","month":"12","year":"2001"},"20011224":{"date":"20011224","cnDay":"一","term":"平安夜","day":"24","month":"12","year":"2001"},"20011225":{"date":"20011225","cnDay":"二","term":"圣诞节","day":"25","month":"12","year":"2001"},"20011226":{"date":"20011226","cnDay":"三","day":"26","value":"毛泽东诞辰","month":"12","year":"2001"},"20011227":{"date":"20011227","cnDay":"四","day":"27","month":"12","year":"2001"},"20011228":{"date":"20011228","cnDay":"五","day":"28","month":"12","year":"2001"},"20011229":{"date":"20011229","cnDay":"六","day":"29","month":"12","year":"2001"},"20011230":{"date":"20011230","cnDay":"日","day":"30","month":"12","year":"2001"},"20011231":{"date":"20011231","cnDay":"一","day":"31","month":"12","year":"2001"},"20020101":{"date":"20020101","cnDay":"二","term":"元旦","day":"1","month":"1","year":"2002"},"20020102":{"date":"20020102","cnDay":"三","day":"2","month":"1","year":"2002"},"20020103":{"date":"20020103","cnDay":"四","day":"3","month":"1","year":"2002"},"20020104":{"date":"20020104","cnDay":"五","day":"4","month":"1","year":"2002"},"20020105":{"date":"20020105","cnDay":"六","term":"小寒","day":"5","month":"1","year":"2002"},"20020106":{"date":"20020106","cnDay":"日","day":"6","month":"1","year":"2002"},"20020107":{"date":"20020107","cnDay":"一","day":"7","month":"1","year":"2002"},"20020108":{"date":"20020108","cnDay":"二","day":"8","month":"1","year":"2002"},"20020109":{"date":"20020109","cnDay":"三","day":"9","month":"1","year":"2002"},"20020110":{"date":"20020110","cnDay":"四","day":"10","month":"1","year":"2002"},"20020111":{"date":"20020111","cnDay":"五","day":"11","month":"1","year":"2002"},"20020112":{"date":"20020112","cnDay":"六","day":"12","month":"1","year":"2002"},"20020113":{"date":"20020113","cnDay":"日","day":"13","month":"1","year":"2002"},"20020114":{"date":"20020114","cnDay":"一","day":"14","month":"1","year":"2002"},"20020115":{"date":"20020115","cnDay":"二","day":"15","month":"1","year":"2002"},"20020116":{"date":"20020116","cnDay":"三","day":"16","month":"1","year":"2002"},"20020117":{"date":"20020117","cnDay":"四","day":"17","month":"1","year":"2002"},"20020118":{"date":"20020118","cnDay":"五","day":"18","month":"1","year":"2002"},"20020119":{"date":"20020119","cnDay":"六","day":"19","month":"1","year":"2002"},"20020120":{"date":"20020120","cnDay":"日","desc":"腊八节","term":"大寒","day":"20","month":"1","year":"2002"},"20020121":{"date":"20020121","cnDay":"一","day":"21","month":"1","year":"2002"},"20020122":{"date":"20020122","cnDay":"二","day":"22","month":"1","year":"2002"},"20020123":{"date":"20020123","cnDay":"三","day":"23","month":"1","year":"2002"},"20020124":{"date":"20020124","cnDay":"四","day":"24","month":"1","year":"2002"},"20020125":{"date":"20020125","cnDay":"五","day":"25","month":"1","year":"2002"},"20020126":{"date":"20020126","cnDay":"六","day":"26","value":"国际海关日","month":"1","year":"2002"},"20020127":{"date":"20020127","cnDay":"日","day":"27","month":"1","year":"2002"},"20020128":{"date":"20020128","cnDay":"一","day":"28","month":"1","year":"2002"},"20020129":{"date":"20020129","cnDay":"二","day":"29","month":"1","year":"2002"},"20020130":{"date":"20020130","cnDay":"三","day":"30","month":"1","year":"2002"},"20020131":{"date":"20020131","cnDay":"四","day":"31","month":"1","year":"2002"},"20020201":{"date":"20020201","cnDay":"五","day":"1","month":"2","year":"2002"},"20020202":{"date":"20020202","cnDay":"六","day":"2","value":"湿地日","month":"2","year":"2002"},"20020203":{"date":"20020203","cnDay":"日","day":"3","month":"2","year":"2002"},"20020204":{"date":"20020204","cnDay":"一","term":"立春 北方小年","day":"4","month":"2","year":"2002"},"20020205":{"date":"20020205","cnDay":"二","term":"南小年","day":"5","month":"2","year":"2002"},"20020206":{"date":"20020206","cnDay":"三","day":"6","month":"2","year":"2002"},"20020207":{"date":"20020207","cnDay":"四","day":"7","month":"2","year":"2002"},"20020208":{"date":"20020208","cnDay":"五","day":"8","month":"2","year":"2002"},"20020209":{"date":"20020209","cnDay":"六","day":"9","month":"2","year":"2002"},"20020210":{"date":"20020210","cnDay":"日","day":"10","value":"国际气象节","month":"2","year":"2002"},"20020211":{"date":"20020211","cnDay":"一","term":"除夕","day":"11","month":"2","year":"2002"},"20020212":{"date":"20020212","cnDay":"二","term":"春节","day":"12","month":"2","year":"2002"},"20020213":{"date":"20020213","cnDay":"三","day":"13","month":"2","year":"2002"},"20020214":{"date":"20020214","cnDay":"四","term":"情人节","day":"14","month":"2","year":"2002"},"20020215":{"date":"20020215","cnDay":"五","day":"15","month":"2","year":"2002"},"20020216":{"date":"20020216","cnDay":"六","day":"16","month":"2","year":"2002"},"20020217":{"date":"20020217","cnDay":"日","day":"17","month":"2","year":"2002"},"20020218":{"date":"20020218","cnDay":"一","day":"18","month":"2","year":"2002"},"20020219":{"date":"20020219","cnDay":"二","term":"雨水","day":"19","month":"2","year":"2002"},"20020220":{"date":"20020220","cnDay":"三","day":"20","month":"2","year":"2002"},"20020221":{"date":"20020221","cnDay":"四","day":"21","month":"2","year":"2002"},"20020222":{"date":"20020222","cnDay":"五","day":"22","month":"2","year":"2002"},"20020223":{"date":"20020223","cnDay":"六","day":"23","month":"2","year":"2002"},"20020224":{"date":"20020224","cnDay":"日","day":"24","month":"2","year":"2002"},"20020225":{"date":"20020225","cnDay":"一","day":"25","month":"2","year":"2002"},"20020226":{"date":"20020226","cnDay":"二","term":"元宵节","day":"26","month":"2","year":"2002"},"20020227":{"date":"20020227","cnDay":"三","day":"27","month":"2","year":"2002"},"20020228":{"date":"20020228","cnDay":"四","day":"28","month":"2","year":"2002"},"20020301":{"date":"20020301","cnDay":"五","day":"1","value":"国际海豹日","month":"3","year":"2002"},"20020302":{"date":"20020302","cnDay":"六","day":"2","month":"3","year":"2002"},"20020303":{"date":"20020303","cnDay":"日","day":"3","value":"全国爱耳日","month":"3","year":"2002"},"20020304":{"date":"20020304","cnDay":"一","day":"4","month":"3","year":"2002"},"20020305":{"date":"20020305","cnDay":"二","day":"5","value":"雷锋纪念日","month":"3","year":"2002"},"20020306":{"date":"20020306","cnDay":"三","term":"惊蛰","day":"6","month":"3","year":"2002"},"20020307":{"date":"20020307","cnDay":"四","day":"7","value":"女生节","month":"3","year":"2002"},"20020308":{"date":"20020308","cnDay":"五","term":"妇女节","day":"8","month":"3","year":"2002"},"20020309":{"date":"20020309","cnDay":"六","day":"9","value":"保护母亲河日","month":"3","year":"2002"},"20020310":{"date":"20020310","cnDay":"日","day":"10","month":"3","year":"2002"},"20020311":{"date":"20020311","cnDay":"一","day":"11","month":"3","year":"2002"},"20020312":{"date":"20020312","cnDay":"二","desc":"植树节","day":"12","month":"3","year":"2002"},"20020313":{"date":"20020313","cnDay":"三","day":"13","month":"3","year":"2002"},"20020314":{"date":"20020314","cnDay":"四","day":"14","value":"国际警察日 白色情人节","month":"3","year":"2002"},"20020315":{"date":"20020315","cnDay":"五","day":"15","value":"龙头节 消费者权益日","month":"3","year":"2002"},"20020316":{"date":"20020316","cnDay":"六","day":"16","month":"3","year":"2002"},"20020317":{"date":"20020317","cnDay":"日","day":"17","value":"国际航海日","month":"3","year":"2002"},"20020318":{"date":"20020318","cnDay":"一","day":"18","value":"全国爱肝日","month":"3","year":"2002"},"20020319":{"date":"20020319","cnDay":"二","day":"19","month":"3","year":"2002"},"20020320":{"date":"20020320","cnDay":"三","day":"20","month":"3","year":"2002"},"20020321":{"date":"20020321","cnDay":"四","term":"春分","day":"21","value":"世界睡眠日 世界儿歌日 世界森林日","month":"3","year":"2002"},"20020322":{"date":"20020322","cnDay":"五","day":"22","value":"世界水日","month":"3","year":"2002"},"20020323":{"date":"20020323","cnDay":"六","day":"23","value":"世界气象日","month":"3","year":"2002"},"20020324":{"date":"20020324","cnDay":"日","day":"24","value":"防治结核病日","month":"3","year":"2002"},"20020325":{"date":"20020325","cnDay":"一","day":"25","value":"学生安全教育日","month":"3","year":"2002"},"20020326":{"date":"20020326","cnDay":"二","day":"26","month":"3","year":"2002"},"20020327":{"date":"20020327","cnDay":"三","day":"27","month":"3","year":"2002"},"20020328":{"date":"20020328","cnDay":"四","day":"28","month":"3","year":"2002"},"20020329":{"date":"20020329","cnDay":"五","day":"29","month":"3","year":"2002"},"20020330":{"date":"20020330","cnDay":"六","day":"30","month":"3","year":"2002"},"20020331":{"date":"20020331","cnDay":"日","day":"31","month":"3","year":"2002"},"20020401":{"date":"20020401","cnDay":"一","term":"愚人节","day":"1","month":"4","year":"2002"},"20020402":{"date":"20020402","cnDay":"二","day":"2","month":"4","year":"2002"},"20020403":{"date":"20020403","cnDay":"三","day":"3","month":"4","year":"2002"},"20020404":{"date":"20020404","cnDay":"四","desc":"寒食节","day":"4","month":"4","year":"2002"},"20020405":{"date":"20020405","cnDay":"五","term":"清明","day":"5","month":"4","year":"2002"},"20020406":{"date":"20020406","cnDay":"六","day":"6","month":"4","year":"2002"},"20020407":{"date":"20020407","cnDay":"日","day":"7","value":"世界卫生日","month":"4","year":"2002"},"20020408":{"date":"20020408","cnDay":"一","day":"8","month":"4","year":"2002"},"20020409":{"date":"20020409","cnDay":"二","day":"9","month":"4","year":"2002"},"20020410":{"date":"20020410","cnDay":"三","day":"10","month":"4","year":"2002"},"20020411":{"date":"20020411","cnDay":"四","day":"11","month":"4","year":"2002"},"20020412":{"date":"20020412","cnDay":"五","day":"12","month":"4","year":"2002"},"20020413":{"date":"20020413","cnDay":"六","day":"13","month":"4","year":"2002"},"20020414":{"date":"20020414","cnDay":"日","day":"14","value":"黑色情人节","month":"4","year":"2002"},"20020415":{"date":"20020415","cnDay":"一","desc":"上巳节","day":"15","month":"4","year":"2002"},"20020416":{"date":"20020416","cnDay":"二","day":"16","month":"4","year":"2002"},"20020417":{"date":"20020417","cnDay":"三","day":"17","month":"4","year":"2002"},"20020418":{"date":"20020418","cnDay":"四","day":"18","month":"4","year":"2002"},"20020419":{"date":"20020419","cnDay":"五","day":"19","month":"4","year":"2002"},"20020420":{"date":"20020420","cnDay":"六","term":"谷雨","day":"20","month":"4","year":"2002"},"20020421":{"date":"20020421","cnDay":"日","day":"21","month":"4","year":"2002"},"20020422":{"date":"20020422","cnDay":"一","day":"22","value":"地球日","month":"4","year":"2002"},"20020423":{"date":"20020423","cnDay":"二","day":"23","value":"世界读书日","month":"4","year":"2002"},"20020424":{"date":"20020424","cnDay":"三","day":"24","month":"4","year":"2002"},"20020425":{"date":"20020425","cnDay":"四","day":"25","month":"4","year":"2002"},"20020426":{"date":"20020426","cnDay":"五","day":"26","value":"知识产权日","month":"4","year":"2002"},"20020427":{"date":"20020427","cnDay":"六","day":"27","month":"4","year":"2002"},"20020428":{"date":"20020428","cnDay":"日","day":"28","month":"4","year":"2002"},"20020429":{"date":"20020429","cnDay":"一","day":"29","month":"4","year":"2002"},"20020430":{"date":"20020430","cnDay":"二","day":"30","month":"4","year":"2002"},"20020501":{"date":"20020501","cnDay":"三","term":"劳动节","day":"1","month":"5","year":"2002"},"20020502":{"date":"20020502","cnDay":"四","day":"2","month":"5","year":"2002"},"20020503":{"date":"20020503","cnDay":"五","day":"3","month":"5","year":"2002"},"20020504":{"date":"20020504","cnDay":"六","term":"青年节","day":"4","value":"青年节","month":"5","year":"2002"},"20020505":{"date":"20020505","cnDay":"日","day":"5","month":"5","year":"2002"},"20020506":{"date":"20020506","cnDay":"一","term":"立夏","day":"6","month":"5","year":"2002"},"20020507":{"date":"20020507","cnDay":"二","day":"7","value":"世界哮喘日","month":"5","year":"2002"},"20020508":{"date":"20020508","cnDay":"三","day":"8","value":"世界微笑日 世界红十字日","month":"5","year":"2002"},"20020509":{"date":"20020509","cnDay":"四","day":"9","month":"5","year":"2002"},"20020510":{"date":"20020510","cnDay":"五","day":"10","month":"5","year":"2002"},"20020511":{"date":"20020511","cnDay":"六","day":"11","month":"5","year":"2002"},"20020512":{"date":"20020512","cnDay":"日","day":"12","value":"护士节","month":"5","year":"2002"},"20020513":{"date":"20020513","cnDay":"一","day":"13","month":"5","year":"2002"},"20020514":{"date":"20020514","cnDay":"二","day":"14","month":"5","year":"2002"},"20020515":{"date":"20020515","cnDay":"三","day":"15","value":"国际家庭日","month":"5","year":"2002"},"20020516":{"date":"20020516","cnDay":"四","day":"16","month":"5","year":"2002"},"20020517":{"date":"20020517","cnDay":"五","day":"17","month":"5","year":"2002"},"20020518":{"date":"20020518","cnDay":"六","day":"18","value":"博物馆日","month":"5","year":"2002"},"20020519":{"date":"20020519","cnDay":"日","day":"19","month":"5","year":"2002"},"20020520":{"date":"20020520","cnDay":"一","day":"20","value":"学生营养日","month":"5","year":"2002"},"20020521":{"date":"20020521","cnDay":"二","term":"小满","day":"21","month":"5","year":"2002"},"20020522":{"date":"20020522","cnDay":"三","day":"22","value":"生物多样性日","month":"5","year":"2002"},"20020523":{"date":"20020523","cnDay":"四","day":"23","month":"5","year":"2002"},"20020524":{"date":"20020524","cnDay":"五","day":"24","month":"5","year":"2002"},"20020525":{"date":"20020525","cnDay":"六","day":"25","month":"5","year":"2002"},"20020526":{"date":"20020526","cnDay":"日","day":"26","month":"5","year":"2002"},"20020527":{"date":"20020527","cnDay":"一","day":"27","month":"5","year":"2002"},"20020528":{"date":"20020528","cnDay":"二","day":"28","month":"5","year":"2002"},"20020529":{"date":"20020529","cnDay":"三","day":"29","month":"5","year":"2002"},"20020530":{"date":"20020530","cnDay":"四","day":"30","month":"5","year":"2002"},"20020531":{"date":"20020531","cnDay":"五","day":"31","value":"世界无烟日","month":"5","year":"2002"},"20020601":{"date":"20020601","cnDay":"六","term":"儿童节","day":"1","month":"6","year":"2002"},"20020602":{"date":"20020602","cnDay":"日","day":"2","month":"6","year":"2002"},"20020603":{"date":"20020603","cnDay":"一","day":"3","month":"6","year":"2002"},"20020604":{"date":"20020604","cnDay":"二","day":"4","month":"6","year":"2002"},"20020605":{"date":"20020605","cnDay":"三","day":"5","value":"环境日","month":"6","year":"2002"},"20020606":{"date":"20020606","cnDay":"四","term":"芒种","day":"6","value":"全国爱眼日","month":"6","year":"2002"},"20020607":{"date":"20020607","cnDay":"五","day":"7","month":"6","year":"2002"},"20020608":{"date":"20020608","cnDay":"六","day":"8","month":"6","year":"2002"},"20020609":{"date":"20020609","cnDay":"日","day":"9","month":"6","year":"2002"},"20020610":{"date":"20020610","cnDay":"一","day":"10","month":"6","year":"2002"},"20020611":{"date":"20020611","cnDay":"二","day":"11","value":"中国人口日","month":"6","year":"2002"},"20020612":{"date":"20020612","cnDay":"三","day":"12","month":"6","year":"2002"},"20020613":{"date":"20020613","cnDay":"四","day":"13","month":"6","year":"2002"},"20020614":{"date":"20020614","cnDay":"五","day":"14","month":"6","year":"2002"},"20020615":{"date":"20020615","cnDay":"六","term":"端午节","day":"15","month":"6","year":"2002","legalHoliday":"端午节"},"20020616":{"date":"20020616","cnDay":"日","term":"父亲节","day":"16","month":"6","year":"2002","legalHoliday":"端午节"},"20020617":{"date":"20020617","cnDay":"一","day":"17","month":"6","year":"2002"},"20020618":{"date":"20020618","cnDay":"二","day":"18","month":"6","year":"2002"},"20020619":{"date":"20020619","cnDay":"三","day":"19","month":"6","year":"2002"},"20020620":{"date":"20020620","cnDay":"四","day":"20","month":"6","year":"2002"},"20020621":{"date":"20020621","cnDay":"五","term":"夏至","day":"21","month":"6","year":"2002"},"20020622":{"date":"20020622","cnDay":"六","day":"22","month":"6","year":"2002"},"20020623":{"date":"20020623","cnDay":"日","day":"23","month":"6","year":"2002"},"20020624":{"date":"20020624","cnDay":"一","day":"24","month":"6","year":"2002"},"20020625":{"date":"20020625","cnDay":"二","day":"25","value":"全国土地日","month":"6","year":"2002"},"20020626":{"date":"20020626","cnDay":"三","day":"26","value":"国际禁毒日","month":"6","year":"2002"},"20020627":{"date":"20020627","cnDay":"四","day":"27","month":"6","year":"2002"},"20020628":{"date":"20020628","cnDay":"五","day":"28","month":"6","year":"2002"},"20020629":{"date":"20020629","cnDay":"六","day":"29","month":"6","year":"2002"},"20020630":{"date":"20020630","cnDay":"日","day":"30","month":"6","year":"2002"},"20020701":{"date":"20020701","cnDay":"一","term":"建党节","day":"1","value":"香港回归日","month":"7","year":"2002"},"20020702":{"date":"20020702","cnDay":"二","day":"2","value":"体育记者日","month":"7","year":"2002"},"20020703":{"date":"20020703","cnDay":"三","day":"3","month":"7","year":"2002"},"20020704":{"date":"20020704","cnDay":"四","day":"4","value":"美国独立日","month":"7","year":"2002"},"20020705":{"date":"20020705","cnDay":"五","day":"5","month":"7","year":"2002"},"20020706":{"date":"20020706","cnDay":"六","day":"6","month":"7","year":"2002"},"20020707":{"date":"20020707","cnDay":"日","term":"小暑","day":"7","month":"7","year":"2002"},"20020708":{"date":"20020708","cnDay":"一","day":"8","month":"7","year":"2002"},"20020709":{"date":"20020709","cnDay":"二","day":"9","month":"7","year":"2002"},"20020710":{"date":"20020710","cnDay":"三","day":"10","month":"7","year":"2002"},"20020711":{"date":"20020711","cnDay":"四","day":"11","value":"世界人口日","month":"7","year":"2002"},"20020712":{"date":"20020712","cnDay":"五","day":"12","month":"7","year":"2002"},"20020713":{"date":"20020713","cnDay":"六","day":"13","month":"7","year":"2002"},"20020714":{"date":"20020714","cnDay":"日","day":"14","value":"银色情人节","month":"7","year":"2002"},"20020715":{"date":"20020715","cnDay":"一","day":"15","month":"7","year":"2002"},"20020716":{"date":"20020716","cnDay":"二","day":"16","month":"7","year":"2002"},"20020717":{"date":"20020717","cnDay":"三","day":"17","month":"7","year":"2002"},"20020718":{"date":"20020718","cnDay":"四","day":"18","month":"7","year":"2002"},"20020719":{"date":"20020719","cnDay":"五","day":"19","month":"7","year":"2002"},"20020720":{"date":"20020720","cnDay":"六","day":"20","month":"7","year":"2002"},"20020721":{"date":"20020721","cnDay":"日","day":"21","month":"7","year":"2002"},"20020722":{"date":"20020722","cnDay":"一","day":"22","month":"7","year":"2002"},"20020723":{"date":"20020723","cnDay":"二","term":"大暑","day":"23","month":"7","year":"2002"},"20020724":{"date":"20020724","cnDay":"三","day":"24","month":"7","year":"2002"},"20020725":{"date":"20020725","cnDay":"四","day":"25","month":"7","year":"2002"},"20020726":{"date":"20020726","cnDay":"五","day":"26","month":"7","year":"2002"},"20020727":{"date":"20020727","cnDay":"六","day":"27","month":"7","year":"2002"},"20020728":{"date":"20020728","cnDay":"日","day":"28","month":"7","year":"2002"},"20020729":{"date":"20020729","cnDay":"一","day":"29","month":"7","year":"2002"},"20020730":{"date":"20020730","cnDay":"二","day":"30","month":"7","year":"2002"},"20020731":{"date":"20020731","cnDay":"三","day":"31","value":"非洲妇女日","month":"7","year":"2002"},"20020801":{"date":"20020801","cnDay":"四","term":"建军节","day":"1","month":"8","year":"2002"},"20020802":{"date":"20020802","cnDay":"五","day":"2","value":"火把节","month":"8","year":"2002"},"20020803":{"date":"20020803","cnDay":"六","day":"3","month":"8","year":"2002"},"20020804":{"date":"20020804","cnDay":"日","day":"4","month":"8","year":"2002"},"20020805":{"date":"20020805","cnDay":"一","day":"5","month":"8","year":"2002"},"20020806":{"date":"20020806","cnDay":"二","day":"6","month":"8","year":"2002"},"20020807":{"date":"20020807","cnDay":"三","day":"7","month":"8","year":"2002"},"20020808":{"date":"20020808","cnDay":"四","term":"立秋","day":"8","month":"8","year":"2002"},"20020809":{"date":"20020809","cnDay":"五","day":"9","month":"8","year":"2002"},"20020810":{"date":"20020810","cnDay":"六","day":"10","month":"8","year":"2002"},"20020811":{"date":"20020811","cnDay":"日","day":"11","month":"8","year":"2002"},"20020812":{"date":"20020812","cnDay":"一","day":"12","value":"国际青年节","month":"8","year":"2002"},"20020813":{"date":"20020813","cnDay":"二","day":"13","month":"8","year":"2002"},"20020814":{"date":"20020814","cnDay":"三","day":"14","month":"8","year":"2002"},"20020815":{"date":"20020815","cnDay":"四","term":"七夕节","day":"15","month":"8","year":"2002"},"20020816":{"date":"20020816","cnDay":"五","day":"16","month":"8","year":"2002"},"20020817":{"date":"20020817","cnDay":"六","day":"17","month":"8","year":"2002"},"20020818":{"date":"20020818","cnDay":"日","day":"18","month":"8","year":"2002"},"20020819":{"date":"20020819","cnDay":"一","day":"19","month":"8","year":"2002"},"20020820":{"date":"20020820","cnDay":"二","day":"20","month":"8","year":"2002"},"20020821":{"date":"20020821","cnDay":"三","day":"21","month":"8","year":"2002"},"20020822":{"date":"20020822","cnDay":"四","day":"22","month":"8","year":"2002"},"20020823":{"date":"20020823","cnDay":"五","desc":"中元节","term":"处暑","day":"23","month":"8","year":"2002"},"20020824":{"date":"20020824","cnDay":"六","day":"24","month":"8","year":"2002"},"20020825":{"date":"20020825","cnDay":"日","day":"25","month":"8","year":"2002"},"20020826":{"date":"20020826","cnDay":"一","day":"26","value":"律师咨询日","month":"8","year":"2002"},"20020827":{"date":"20020827","cnDay":"二","day":"27","month":"8","year":"2002"},"20020828":{"date":"20020828","cnDay":"三","day":"28","month":"8","year":"2002"},"20020829":{"date":"20020829","cnDay":"四","day":"29","month":"8","year":"2002"},"20020830":{"date":"20020830","cnDay":"五","day":"30","month":"8","year":"2002"},"20020831":{"date":"20020831","cnDay":"六","day":"31","month":"8","year":"2002"},"20020901":{"date":"20020901","cnDay":"日","day":"1","month":"9","year":"2002"},"20020902":{"date":"20020902","cnDay":"一","day":"2","month":"9","year":"2002"},"20020903":{"date":"20020903","cnDay":"二","day":"3","month":"9","year":"2002"},"20020904":{"date":"20020904","cnDay":"三","day":"4","month":"9","year":"2002"},"20020905":{"date":"20020905","cnDay":"四","day":"5","month":"9","year":"2002"},"20020906":{"date":"20020906","cnDay":"五","day":"6","month":"9","year":"2002"},"20020907":{"date":"20020907","cnDay":"六","day":"7","month":"9","year":"2002"},"20020908":{"date":"20020908","cnDay":"日","term":"白露","day":"8","value":"国际扫盲日 新闻工作者日","month":"9","year":"2002"},"20020909":{"date":"20020909","cnDay":"一","day":"9","month":"9","year":"2002"},"20020910":{"date":"20020910","cnDay":"二","term":"教师节","day":"10","month":"9","year":"2002"},"20020911":{"date":"20020911","cnDay":"三","day":"11","month":"9","year":"2002"},"20020912":{"date":"20020912","cnDay":"四","day":"12","month":"9","year":"2002"},"20020913":{"date":"20020913","cnDay":"五","day":"13","month":"9","year":"2002"},"20020914":{"date":"20020914","cnDay":"六","day":"14","month":"9","year":"2002"},"20020915":{"date":"20020915","cnDay":"日","day":"15","value":"清洁地球日","month":"9","year":"2002"},"20020916":{"date":"20020916","cnDay":"一","day":"16","value":"中国脑健康日 臭氧层保护日","month":"9","year":"2002"},"20020917":{"date":"20020917","cnDay":"二","day":"17","month":"9","year":"2002"},"20020918":{"date":"20020918","cnDay":"三","day":"18","value":"九一八纪念日","month":"9","year":"2002"},"20020919":{"date":"20020919","cnDay":"四","day":"19","month":"9","year":"2002"},"20020920":{"date":"20020920","cnDay":"五","day":"20","value":"全国爱牙日","month":"9","year":"2002"},"20020921":{"date":"20020921","cnDay":"六","term":"中秋节","day":"21","value":"国际和平日","month":"9","year":"2002"},"20020922":{"date":"20020922","cnDay":"日","day":"22","month":"9","year":"2002"},"20020923":{"date":"20020923","cnDay":"一","term":"秋分","day":"23","month":"9","year":"2002"},"20020924":{"date":"20020924","cnDay":"二","day":"24","month":"9","year":"2002"},"20020925":{"date":"20020925","cnDay":"三","day":"25","month":"9","year":"2002"},"20020926":{"date":"20020926","cnDay":"四","day":"26","month":"9","year":"2002"},"20020927":{"date":"20020927","cnDay":"五","day":"27","value":"世界旅游日","month":"9","year":"2002"},"20020928":{"date":"20020928","cnDay":"六","day":"28","month":"9","year":"2002"},"20020929":{"date":"20020929","cnDay":"日","day":"29","month":"9","year":"2002"},"20020930":{"date":"20020930","cnDay":"一","day":"30","month":"9","year":"2002"},"20021001":{"date":"20021001","cnDay":"二","term":"国庆节","day":"1","value":"国际音乐日","month":"10","year":"2002"},"20021002":{"date":"20021002","cnDay":"三","day":"2","month":"10","year":"2002"},"20021003":{"date":"20021003","cnDay":"四","day":"3","month":"10","year":"2002"},"20021004":{"date":"20021004","cnDay":"五","day":"4","value":"世界动物日","month":"10","year":"2002"},"20021005":{"date":"20021005","cnDay":"六","day":"5","value":"世界教师日","month":"10","year":"2002"},"20021006":{"date":"20021006","cnDay":"日","day":"6","month":"10","year":"2002"},"20021007":{"date":"20021007","cnDay":"一","day":"7","month":"10","year":"2002"},"20021008":{"date":"20021008","cnDay":"二","term":"寒露","day":"8","value":"全国高血压日","month":"10","year":"2002"},"20021009":{"date":"20021009","cnDay":"三","day":"9","value":"世界邮政日","month":"10","year":"2002"},"20021010":{"date":"20021010","cnDay":"四","day":"10","month":"10","year":"2002"},"20021011":{"date":"20021011","cnDay":"五","day":"11","month":"10","year":"2002"},"20021012":{"date":"20021012","cnDay":"六","day":"12","month":"10","year":"2002"},"20021013":{"date":"20021013","cnDay":"日","day":"13","month":"10","year":"2002"},"20021014":{"date":"20021014","cnDay":"一","term":"重阳节","day":"14","month":"10","year":"2002"},"20021015":{"date":"20021015","cnDay":"二","day":"15","value":"国际盲人节","month":"10","year":"2002"},"20021016":{"date":"20021016","cnDay":"三","day":"16","value":"世界粮食日","month":"10","year":"2002"},"20021017":{"date":"20021017","cnDay":"四","day":"17","month":"10","year":"2002"},"20021018":{"date":"20021018","cnDay":"五","day":"18","month":"10","year":"2002"},"20021019":{"date":"20021019","cnDay":"六","day":"19","month":"10","year":"2002"},"20021020":{"date":"20021020","cnDay":"日","day":"20","month":"10","year":"2002"},"20021021":{"date":"20021021","cnDay":"一","day":"21","month":"10","year":"2002"},"20021022":{"date":"20021022","cnDay":"二","day":"22","month":"10","year":"2002"},"20021023":{"date":"20021023","cnDay":"三","term":"霜降","day":"23","month":"10","year":"2002"},"20021024":{"date":"20021024","cnDay":"四","day":"24","value":"联合国日","month":"10","year":"2002"},"20021025":{"date":"20021025","cnDay":"五","day":"25","month":"10","year":"2002"},"20021026":{"date":"20021026","cnDay":"六","day":"26","month":"10","year":"2002"},"20021027":{"date":"20021027","cnDay":"日","day":"27","month":"10","year":"2002"},"20021028":{"date":"20021028","cnDay":"一","day":"28","month":"10","year":"2002"},"20021029":{"date":"20021029","cnDay":"二","day":"29","month":"10","year":"2002"},"20021030":{"date":"20021030","cnDay":"三","day":"30","month":"10","year":"2002"},"20021031":{"date":"20021031","cnDay":"四","term":"万圣夜","day":"31","month":"10","year":"2002"},"20021101":{"date":"20021101","cnDay":"五","term":"万圣节","day":"1","month":"11","year":"2002"},"20021102":{"date":"20021102","cnDay":"六","day":"2","month":"11","year":"2002"},"20021103":{"date":"20021103","cnDay":"日","day":"3","month":"11","year":"2002"},"20021104":{"date":"20021104","cnDay":"一","day":"4","month":"11","year":"2002"},"20021105":{"date":"20021105","cnDay":"二","day":"5","value":"寒衣节","month":"11","year":"2002"},"20021106":{"date":"20021106","cnDay":"三","day":"6","month":"11","year":"2002"},"20021107":{"date":"20021107","cnDay":"四","term":"立冬","day":"7","month":"11","year":"2002"},"20021108":{"date":"20021108","cnDay":"五","day":"8","value":"记者节","month":"11","year":"2002"},"20021109":{"date":"20021109","cnDay":"六","day":"9","value":"消防宣传日","month":"11","year":"2002"},"20021110":{"date":"20021110","cnDay":"日","day":"10","month":"11","year":"2002"},"20021111":{"date":"20021111","cnDay":"一","day":"11","month":"11","year":"2002"},"20021112":{"date":"20021112","cnDay":"二","day":"12","month":"11","year":"2002"},"20021113":{"date":"20021113","cnDay":"三","day":"13","month":"11","year":"2002"},"20021114":{"date":"20021114","cnDay":"四","day":"14","value":"世界糖尿病日","month":"11","year":"2002"},"20021115":{"date":"20021115","cnDay":"五","day":"15","month":"11","year":"2002"},"20021116":{"date":"20021116","cnDay":"六","day":"16","month":"11","year":"2002"},"20021117":{"date":"20021117","cnDay":"日","day":"17","value":"学生日","month":"11","year":"2002"},"20021118":{"date":"20021118","cnDay":"一","day":"18","month":"11","year":"2002"},"20021119":{"date":"20021119","cnDay":"二","desc":"下元节","day":"19","month":"11","year":"2002"},"20021120":{"date":"20021120","cnDay":"三","day":"20","month":"11","year":"2002"},"20021121":{"date":"20021121","cnDay":"四","day":"21","month":"11","year":"2002"},"20021122":{"date":"20021122","cnDay":"五","term":"小雪","day":"22","month":"11","year":"2002"},"20021123":{"date":"20021123","cnDay":"六","day":"23","month":"11","year":"2002"},"20021124":{"date":"20021124","cnDay":"日","day":"24","month":"11","year":"2002"},"20021125":{"date":"20021125","cnDay":"一","day":"25","month":"11","year":"2002"},"20021126":{"date":"20021126","cnDay":"二","day":"26","month":"11","year":"2002"},"20021127":{"date":"20021127","cnDay":"三","day":"27","month":"11","year":"2002"},"20021128":{"date":"20021128","cnDay":"四","term":"感恩节","day":"28","month":"11","year":"2002"},"20021129":{"date":"20021129","cnDay":"五","day":"29","month":"11","year":"2002"},"20021130":{"date":"20021130","cnDay":"六","day":"30","month":"11","year":"2002"},"20021201":{"date":"20021201","cnDay":"日","day":"1","value":"艾滋病日","month":"12","year":"2002"},"20021202":{"date":"20021202","cnDay":"一","day":"2","month":"12","year":"2002"},"20021203":{"date":"20021203","cnDay":"二","day":"3","value":"国际残疾人日","month":"12","year":"2002"},"20021204":{"date":"20021204","cnDay":"三","day":"4","month":"12","year":"2002"},"20021205":{"date":"20021205","cnDay":"四","day":"5","month":"12","year":"2002"},"20021206":{"date":"20021206","cnDay":"五","day":"6","month":"12","year":"2002"},"20021207":{"date":"20021207","cnDay":"六","term":"大雪","day":"7","month":"12","year":"2002"},"20021208":{"date":"20021208","cnDay":"日","day":"8","month":"12","year":"2002"},"20021209":{"date":"20021209","cnDay":"一","day":"9","month":"12","year":"2002"},"20021210":{"date":"20021210","cnDay":"二","day":"10","value":"世界人权日","month":"12","year":"2002"},"20021211":{"date":"20021211","cnDay":"三","day":"11","month":"12","year":"2002"},"20021212":{"date":"20021212","cnDay":"四","day":"12","month":"12","year":"2002"},"20021213":{"date":"20021213","cnDay":"五","day":"13","month":"12","year":"2002"},"20021214":{"date":"20021214","cnDay":"六","day":"14","month":"12","year":"2002"},"20021215":{"date":"20021215","cnDay":"日","day":"15","value":"强化免疫日","month":"12","year":"2002"},"20021216":{"date":"20021216","cnDay":"一","day":"16","month":"12","year":"2002"},"20021217":{"date":"20021217","cnDay":"二","day":"17","month":"12","year":"2002"},"20021218":{"date":"20021218","cnDay":"三","day":"18","month":"12","year":"2002"},"20021219":{"date":"20021219","cnDay":"四","day":"19","month":"12","year":"2002"},"20021220":{"date":"20021220","cnDay":"五","day":"20","month":"12","year":"2002"},"20021221":{"date":"20021221","cnDay":"六","day":"21","month":"12","year":"2002"},"20021222":{"date":"20021222","cnDay":"日","term":"冬至","day":"22","month":"12","year":"2002"},"20021223":{"date":"20021223","cnDay":"一","day":"23","month":"12","year":"2002"},"20021224":{"date":"20021224","cnDay":"二","term":"平安夜","day":"24","month":"12","year":"2002"},"20021225":{"date":"20021225","cnDay":"三","term":"圣诞节","day":"25","month":"12","year":"2002"},"20021226":{"date":"20021226","cnDay":"四","day":"26","value":"毛泽东诞辰","month":"12","year":"2002"},"20021227":{"date":"20021227","cnDay":"五","day":"27","month":"12","year":"2002"},"20021228":{"date":"20021228","cnDay":"六","day":"28","month":"12","year":"2002"},"20021229":{"date":"20021229","cnDay":"日","day":"29","month":"12","year":"2002"},"20021230":{"date":"20021230","cnDay":"一","day":"30","month":"12","year":"2002"},"20021231":{"date":"20021231","cnDay":"二","day":"31","month":"12","year":"2002"}}